[{"name":"Admin","description":"com.jluqgon214.hogarmate.components.AdminNavegationBarItems.Admin","location":"app/com.jluqgon214.hogarmate.components/-admin-navegation-bar-items/-admin/index.html","searchKeys":["Admin","Admin","com.jluqgon214.hogarmate.components.AdminNavegationBarItems.Admin"]},{"name":"Home","description":"com.jluqgon214.hogarmate.components.AdminNavegationBarItems.Home","location":"app/com.jluqgon214.hogarmate.components/-admin-navegation-bar-items/-home/index.html","searchKeys":["Home","Home","com.jluqgon214.hogarmate.components.AdminNavegationBarItems.Home"]},{"name":"Home","description":"com.jluqgon214.hogarmate.components.NavegationBarItems.Home","location":"app/com.jluqgon214.hogarmate.components/-navegation-bar-items/-home/index.html","searchKeys":["Home","Home","com.jluqgon214.hogarmate.components.NavegationBarItems.Home"]},{"name":"Profile","description":"com.jluqgon214.hogarmate.components.AdminNavegationBarItems.Profile","location":"app/com.jluqgon214.hogarmate.components/-admin-navegation-bar-items/-profile/index.html","searchKeys":["Profile","Profile","com.jluqgon214.hogarmate.components.AdminNavegationBarItems.Profile"]},{"name":"Profile","description":"com.jluqgon214.hogarmate.components.NavegationBarItems.Profile","location":"app/com.jluqgon214.hogarmate.components/-navegation-bar-items/-profile/index.html","searchKeys":["Profile","Profile","com.jluqgon214.hogarmate.components.NavegationBarItems.Profile"]},{"name":"Settings","description":"com.jluqgon214.hogarmate.components.AdminNavegationBarItems.Settings","location":"app/com.jluqgon214.hogarmate.components/-admin-navegation-bar-items/-settings/index.html","searchKeys":["Settings","Settings","com.jluqgon214.hogarmate.components.AdminNavegationBarItems.Settings"]},{"name":"Settings","description":"com.jluqgon214.hogarmate.components.NavegationBarItems.Settings","location":"app/com.jluqgon214.hogarmate.components/-navegation-bar-items/-settings/index.html","searchKeys":["Settings","Settings","com.jluqgon214.hogarmate.components.NavegationBarItems.Settings"]},{"name":"Tasks","description":"com.jluqgon214.hogarmate.components.AdminNavegationBarItems.Tasks","location":"app/com.jluqgon214.hogarmate.components/-admin-navegation-bar-items/-tasks/index.html","searchKeys":["Tasks","Tasks","com.jluqgon214.hogarmate.components.AdminNavegationBarItems.Tasks"]},{"name":"Tasks","description":"com.jluqgon214.hogarmate.components.NavegationBarItems.Tasks","location":"app/com.jluqgon214.hogarmate.components/-navegation-bar-items/-tasks/index.html","searchKeys":["Tasks","Tasks","com.jluqgon214.hogarmate.components.NavegationBarItems.Tasks"]},{"name":"abstract fun actualizarUsuario(usuario: Usuario): Call<Usuario>","description":"com.jluqgon214.hogarmate.service.ApiService.actualizarUsuario","location":"app/com.jluqgon214.hogarmate.service/-api-service/actualizar-usuario.html","searchKeys":["actualizarUsuario","abstract fun actualizarUsuario(usuario: Usuario): Call<Usuario>","com.jluqgon214.hogarmate.service.ApiService.actualizarUsuario"]},{"name":"abstract fun comprobarAdmin(): Call<Boolean>","description":"com.jluqgon214.hogarmate.service.ApiService.comprobarAdmin","location":"app/com.jluqgon214.hogarmate.service/-api-service/comprobar-admin.html","searchKeys":["comprobarAdmin","abstract fun comprobarAdmin(): Call<Boolean>","com.jluqgon214.hogarmate.service.ApiService.comprobarAdmin"]},{"name":"abstract fun crearTarea(tarea: CrearTareaDTO): Call<Tarea>","description":"com.jluqgon214.hogarmate.service.ApiService.crearTarea","location":"app/com.jluqgon214.hogarmate.service/-api-service/crear-tarea.html","searchKeys":["crearTarea","abstract fun crearTarea(tarea: CrearTareaDTO): Call<Tarea>","com.jluqgon214.hogarmate.service.ApiService.crearTarea"]},{"name":"abstract fun crearTareaUsuario(idUsuario: String?, tarea: CrearTareaDTO): Call<Tarea>","description":"com.jluqgon214.hogarmate.service.ApiService.crearTareaUsuario","location":"app/com.jluqgon214.hogarmate.service/-api-service/crear-tarea-usuario.html","searchKeys":["crearTareaUsuario","abstract fun crearTareaUsuario(idUsuario: String?, tarea: CrearTareaDTO): Call<Tarea>","com.jluqgon214.hogarmate.service.ApiService.crearTareaUsuario"]},{"name":"abstract fun login(request: LoginRequest): Call<LoginResponse>","description":"com.jluqgon214.hogarmate.service.ApiService.login","location":"app/com.jluqgon214.hogarmate.service/-api-service/login.html","searchKeys":["login","abstract fun login(request: LoginRequest): Call<LoginResponse>","com.jluqgon214.hogarmate.service.ApiService.login"]},{"name":"abstract fun obtenerTareasUsuario(): Call<List<Tarea>>","description":"com.jluqgon214.hogarmate.service.ApiService.obtenerTareasUsuario","location":"app/com.jluqgon214.hogarmate.service/-api-service/obtener-tareas-usuario.html","searchKeys":["obtenerTareasUsuario","abstract fun obtenerTareasUsuario(): Call<List<Tarea>>","com.jluqgon214.hogarmate.service.ApiService.obtenerTareasUsuario"]},{"name":"abstract fun obtenerUsuario(): Call<Usuario>","description":"com.jluqgon214.hogarmate.service.ApiService.obtenerUsuario","location":"app/com.jluqgon214.hogarmate.service/-api-service/obtener-usuario.html","searchKeys":["obtenerUsuario","abstract fun obtenerUsuario(): Call<Usuario>","com.jluqgon214.hogarmate.service.ApiService.obtenerUsuario"]},{"name":"abstract fun obtenerUsuariosConTareas(): Call<List<UsuarioConTareasDTO>>","description":"com.jluqgon214.hogarmate.service.ApiService.obtenerUsuariosConTareas","location":"app/com.jluqgon214.hogarmate.service/-api-service/obtener-usuarios-con-tareas.html","searchKeys":["obtenerUsuariosConTareas","abstract fun obtenerUsuariosConTareas(): Call<List<UsuarioConTareasDTO>>","com.jluqgon214.hogarmate.service.ApiService.obtenerUsuariosConTareas"]},{"name":"abstract fun register(request: RegisterRequest): Call<RegisterResponse>","description":"com.jluqgon214.hogarmate.service.ApiService.register","location":"app/com.jluqgon214.hogarmate.service/-api-service/register.html","searchKeys":["register","abstract fun register(request: RegisterRequest): Call<RegisterResponse>","com.jluqgon214.hogarmate.service.ApiService.register"]},{"name":"abstract suspend fun actualizarEstadoTarea(id: String?): Call<Tarea>","description":"com.jluqgon214.hogarmate.service.ApiService.actualizarEstadoTarea","location":"app/com.jluqgon214.hogarmate.service/-api-service/actualizar-estado-tarea.html","searchKeys":["actualizarEstadoTarea","abstract suspend fun actualizarEstadoTarea(id: String?): Call<Tarea>","com.jluqgon214.hogarmate.service.ApiService.actualizarEstadoTarea"]},{"name":"abstract suspend fun eliminarTarea(id: String?): Call<Unit>","description":"com.jluqgon214.hogarmate.service.ApiService.eliminarTarea","location":"app/com.jluqgon214.hogarmate.service/-api-service/eliminar-tarea.html","searchKeys":["eliminarTarea","abstract suspend fun eliminarTarea(id: String?): Call<Unit>","com.jluqgon214.hogarmate.service.ApiService.eliminarTarea"]},{"name":"class AdminViewModel : ViewModel","description":"com.jluqgon214.hogarmate.viewModel.AdminViewModel","location":"app/com.jluqgon214.hogarmate.viewModel/-admin-view-model/index.html","searchKeys":["AdminViewModel","class AdminViewModel : ViewModel","com.jluqgon214.hogarmate.viewModel.AdminViewModel"]},{"name":"class AppViewModel : ViewModel","description":"com.jluqgon214.hogarmate.viewModel.AppViewModel","location":"app/com.jluqgon214.hogarmate.viewModel/-app-view-model/index.html","searchKeys":["AppViewModel","class AppViewModel : ViewModel","com.jluqgon214.hogarmate.viewModel.AppViewModel"]},{"name":"class AuthInterceptor(tokenProvider: () -> String?) : Interceptor","description":"com.jluqgon214.hogarmate.client.AuthInterceptor","location":"app/com.jluqgon214.hogarmate.client/-auth-interceptor/index.html","searchKeys":["AuthInterceptor","class AuthInterceptor(tokenProvider: () -> String?) : Interceptor","com.jluqgon214.hogarmate.client.AuthInterceptor"]},{"name":"class LoginRepository","description":"com.jluqgon214.hogarmate.repository.LoginRepository","location":"app/com.jluqgon214.hogarmate.repository/-login-repository/index.html","searchKeys":["LoginRepository","class LoginRepository","com.jluqgon214.hogarmate.repository.LoginRepository"]},{"name":"class LoginViewModel : ViewModel","description":"com.jluqgon214.hogarmate.viewModel.LoginViewModel","location":"app/com.jluqgon214.hogarmate.viewModel/-login-view-model/index.html","searchKeys":["LoginViewModel","class LoginViewModel : ViewModel","com.jluqgon214.hogarmate.viewModel.LoginViewModel"]},{"name":"class MainActivity : ComponentActivity","description":"com.jluqgon214.hogarmate.MainActivity","location":"app/com.jluqgon214.hogarmate/-main-activity/index.html","searchKeys":["MainActivity","class MainActivity : ComponentActivity","com.jluqgon214.hogarmate.MainActivity"]},{"name":"class ProfileViewModel : ViewModel","description":"com.jluqgon214.hogarmate.viewModel.ProfileViewModel","location":"app/com.jluqgon214.hogarmate.viewModel/-profile-view-model/index.html","searchKeys":["ProfileViewModel","class ProfileViewModel : ViewModel","com.jluqgon214.hogarmate.viewModel.ProfileViewModel"]},{"name":"class RegisterRepository","description":"com.jluqgon214.hogarmate.repository.RegisterRepository","location":"app/com.jluqgon214.hogarmate.repository/-register-repository/index.html","searchKeys":["RegisterRepository","class RegisterRepository","com.jluqgon214.hogarmate.repository.RegisterRepository"]},{"name":"class RegisterViewModel : ViewModel","description":"com.jluqgon214.hogarmate.viewModel.RegisterViewModel","location":"app/com.jluqgon214.hogarmate.viewModel/-register-view-model/index.html","searchKeys":["RegisterViewModel","class RegisterViewModel : ViewModel","com.jluqgon214.hogarmate.viewModel.RegisterViewModel"]},{"name":"class TasksViewModel : ViewModel","description":"com.jluqgon214.hogarmate.viewModel.TasksViewModel","location":"app/com.jluqgon214.hogarmate.viewModel/-tasks-view-model/index.html","searchKeys":["TasksViewModel","class TasksViewModel : ViewModel","com.jluqgon214.hogarmate.viewModel.TasksViewModel"]},{"name":"class ThemePreferences(context: Context)","description":"com.jluqgon214.hogarmate.preferences.ThemePreferences","location":"app/com.jluqgon214.hogarmate.preferences/-theme-preferences/index.html","searchKeys":["ThemePreferences","class ThemePreferences(context: Context)","com.jluqgon214.hogarmate.preferences.ThemePreferences"]},{"name":"class ThemeViewModel(context: Context) : ViewModel","description":"com.jluqgon214.hogarmate.viewModel.ThemeViewModel","location":"app/com.jluqgon214.hogarmate.viewModel/-theme-view-model/index.html","searchKeys":["ThemeViewModel","class ThemeViewModel(context: Context) : ViewModel","com.jluqgon214.hogarmate.viewModel.ThemeViewModel"]},{"name":"constructor()","description":"com.jluqgon214.hogarmate.MainActivity.MainActivity","location":"app/com.jluqgon214.hogarmate/-main-activity/-main-activity.html","searchKeys":["MainActivity","constructor()","com.jluqgon214.hogarmate.MainActivity.MainActivity"]},{"name":"constructor()","description":"com.jluqgon214.hogarmate.repository.LoginRepository.LoginRepository","location":"app/com.jluqgon214.hogarmate.repository/-login-repository/-login-repository.html","searchKeys":["LoginRepository","constructor()","com.jluqgon214.hogarmate.repository.LoginRepository.LoginRepository"]},{"name":"constructor()","description":"com.jluqgon214.hogarmate.repository.RegisterRepository.RegisterRepository","location":"app/com.jluqgon214.hogarmate.repository/-register-repository/-register-repository.html","searchKeys":["RegisterRepository","constructor()","com.jluqgon214.hogarmate.repository.RegisterRepository.RegisterRepository"]},{"name":"constructor()","description":"com.jluqgon214.hogarmate.viewModel.AdminViewModel.AdminViewModel","location":"app/com.jluqgon214.hogarmate.viewModel/-admin-view-model/-admin-view-model.html","searchKeys":["AdminViewModel","constructor()","com.jluqgon214.hogarmate.viewModel.AdminViewModel.AdminViewModel"]},{"name":"constructor()","description":"com.jluqgon214.hogarmate.viewModel.AppViewModel.AppViewModel","location":"app/com.jluqgon214.hogarmate.viewModel/-app-view-model/-app-view-model.html","searchKeys":["AppViewModel","constructor()","com.jluqgon214.hogarmate.viewModel.AppViewModel.AppViewModel"]},{"name":"constructor()","description":"com.jluqgon214.hogarmate.viewModel.LoginViewModel.LoginViewModel","location":"app/com.jluqgon214.hogarmate.viewModel/-login-view-model/-login-view-model.html","searchKeys":["LoginViewModel","constructor()","com.jluqgon214.hogarmate.viewModel.LoginViewModel.LoginViewModel"]},{"name":"constructor()","description":"com.jluqgon214.hogarmate.viewModel.ProfileViewModel.ProfileViewModel","location":"app/com.jluqgon214.hogarmate.viewModel/-profile-view-model/-profile-view-model.html","searchKeys":["ProfileViewModel","constructor()","com.jluqgon214.hogarmate.viewModel.ProfileViewModel.ProfileViewModel"]},{"name":"constructor()","description":"com.jluqgon214.hogarmate.viewModel.RegisterViewModel.RegisterViewModel","location":"app/com.jluqgon214.hogarmate.viewModel/-register-view-model/-register-view-model.html","searchKeys":["RegisterViewModel","constructor()","com.jluqgon214.hogarmate.viewModel.RegisterViewModel.RegisterViewModel"]},{"name":"constructor()","description":"com.jluqgon214.hogarmate.viewModel.TasksViewModel.TasksViewModel","location":"app/com.jluqgon214.hogarmate.viewModel/-tasks-view-model/-tasks-view-model.html","searchKeys":["TasksViewModel","constructor()","com.jluqgon214.hogarmate.viewModel.TasksViewModel.TasksViewModel"]},{"name":"constructor(_id: String, username: String, password: String, email: String, roles: String, hogar: String? = null)","description":"com.jluqgon214.hogarmate.model.Usuario.Usuario","location":"app/com.jluqgon214.hogarmate.model/-usuario/-usuario.html","searchKeys":["Usuario","constructor(_id: String, username: String, password: String, email: String, roles: String, hogar: String? = null)","com.jluqgon214.hogarmate.model.Usuario.Usuario"]},{"name":"constructor(_id: String? = null, descripcion: String, completada: Boolean, usuario: Usuario)","description":"com.jluqgon214.hogarmate.model.Tarea.Tarea","location":"app/com.jluqgon214.hogarmate.model/-tarea/-tarea.html","searchKeys":["Tarea","constructor(_id: String? = null, descripcion: String, completada: Boolean, usuario: Usuario)","com.jluqgon214.hogarmate.model.Tarea.Tarea"]},{"name":"constructor(_id: String?, descripcion: String, completada: Boolean)","description":"com.jluqgon214.hogarmate.model.DTO.TareaDTO.TareaDTO","location":"app/com.jluqgon214.hogarmate.model.DTO/-tarea-d-t-o/-tarea-d-t-o.html","searchKeys":["TareaDTO","constructor(_id: String?, descripcion: String, completada: Boolean)","com.jluqgon214.hogarmate.model.DTO.TareaDTO.TareaDTO"]},{"name":"constructor(_id: String?, username: String, email: String, roles: String, tareas: List<TareaDTO>)","description":"com.jluqgon214.hogarmate.model.DTO.UsuarioConTareasDTO.UsuarioConTareasDTO","location":"app/com.jluqgon214.hogarmate.model.DTO/-usuario-con-tareas-d-t-o/-usuario-con-tareas-d-t-o.html","searchKeys":["UsuarioConTareasDTO","constructor(_id: String?, username: String, email: String, roles: String, tareas: List<TareaDTO>)","com.jluqgon214.hogarmate.model.DTO.UsuarioConTareasDTO.UsuarioConTareasDTO"]},{"name":"constructor(context: Context)","description":"com.jluqgon214.hogarmate.preferences.ThemePreferences.ThemePreferences","location":"app/com.jluqgon214.hogarmate.preferences/-theme-preferences/-theme-preferences.html","searchKeys":["ThemePreferences","constructor(context: Context)","com.jluqgon214.hogarmate.preferences.ThemePreferences.ThemePreferences"]},{"name":"constructor(context: Context)","description":"com.jluqgon214.hogarmate.viewModel.ThemeViewModel.ThemeViewModel","location":"app/com.jluqgon214.hogarmate.viewModel/-theme-view-model/-theme-view-model.html","searchKeys":["ThemeViewModel","constructor(context: Context)","com.jluqgon214.hogarmate.viewModel.ThemeViewModel.ThemeViewModel"]},{"name":"constructor(descripcion: String)","description":"com.jluqgon214.hogarmate.model.DTO.CrearTareaDTO.CrearTareaDTO","location":"app/com.jluqgon214.hogarmate.model.DTO/-crear-tarea-d-t-o/-crear-tarea-d-t-o.html","searchKeys":["CrearTareaDTO","constructor(descripcion: String)","com.jluqgon214.hogarmate.model.DTO.CrearTareaDTO.CrearTareaDTO"]},{"name":"constructor(email: String, password: String)","description":"com.jluqgon214.hogarmate.model.LoginRequest.LoginRequest","location":"app/com.jluqgon214.hogarmate.model/-login-request/-login-request.html","searchKeys":["LoginRequest","constructor(email: String, password: String)","com.jluqgon214.hogarmate.model.LoginRequest.LoginRequest"]},{"name":"constructor(message: String)","description":"com.jluqgon214.hogarmate.model.RegisterResponse.RegisterResponse","location":"app/com.jluqgon214.hogarmate.model/-register-response/-register-response.html","searchKeys":["RegisterResponse","constructor(message: String)","com.jluqgon214.hogarmate.model.RegisterResponse.RegisterResponse"]},{"name":"constructor(token: String)","description":"com.jluqgon214.hogarmate.model.LoginResponse.LoginResponse","location":"app/com.jluqgon214.hogarmate.model/-login-response/-login-response.html","searchKeys":["LoginResponse","constructor(token: String)","com.jluqgon214.hogarmate.model.LoginResponse.LoginResponse"]},{"name":"constructor(tokenProvider: () -> String?)","description":"com.jluqgon214.hogarmate.client.AuthInterceptor.AuthInterceptor","location":"app/com.jluqgon214.hogarmate.client/-auth-interceptor/-auth-interceptor.html","searchKeys":["AuthInterceptor","constructor(tokenProvider: () -> String?)","com.jluqgon214.hogarmate.client.AuthInterceptor.AuthInterceptor"]},{"name":"constructor(username: String, email: String, password: String, passwordRepeat: String, rol: String? = \"USER\", hogar: String? = null)","description":"com.jluqgon214.hogarmate.model.RegisterRequest.RegisterRequest","location":"app/com.jluqgon214.hogarmate.model/-register-request/-register-request.html","searchKeys":["RegisterRequest","constructor(username: String, email: String, password: String, passwordRepeat: String, rol: String? = \"USER\", hogar: String? = null)","com.jluqgon214.hogarmate.model.RegisterRequest.RegisterRequest"]},{"name":"data class CrearTareaDTO(val descripcion: String)","description":"com.jluqgon214.hogarmate.model.DTO.CrearTareaDTO","location":"app/com.jluqgon214.hogarmate.model.DTO/-crear-tarea-d-t-o/index.html","searchKeys":["CrearTareaDTO","data class CrearTareaDTO(val descripcion: String)","com.jluqgon214.hogarmate.model.DTO.CrearTareaDTO"]},{"name":"data class LoginRequest(val email: String, val password: String)","description":"com.jluqgon214.hogarmate.model.LoginRequest","location":"app/com.jluqgon214.hogarmate.model/-login-request/index.html","searchKeys":["LoginRequest","data class LoginRequest(val email: String, val password: String)","com.jluqgon214.hogarmate.model.LoginRequest"]},{"name":"data class LoginResponse(val token: String)","description":"com.jluqgon214.hogarmate.model.LoginResponse","location":"app/com.jluqgon214.hogarmate.model/-login-response/index.html","searchKeys":["LoginResponse","data class LoginResponse(val token: String)","com.jluqgon214.hogarmate.model.LoginResponse"]},{"name":"data class RegisterRequest(val username: String, val email: String, val password: String, val passwordRepeat: String, val rol: String? = \"USER\", val hogar: String? = null)","description":"com.jluqgon214.hogarmate.model.RegisterRequest","location":"app/com.jluqgon214.hogarmate.model/-register-request/index.html","searchKeys":["RegisterRequest","data class RegisterRequest(val username: String, val email: String, val password: String, val passwordRepeat: String, val rol: String? = \"USER\", val hogar: String? = null)","com.jluqgon214.hogarmate.model.RegisterRequest"]},{"name":"data class RegisterResponse(val message: String)","description":"com.jluqgon214.hogarmate.model.RegisterResponse","location":"app/com.jluqgon214.hogarmate.model/-register-response/index.html","searchKeys":["RegisterResponse","data class RegisterResponse(val message: String)","com.jluqgon214.hogarmate.model.RegisterResponse"]},{"name":"data class Tarea(val _id: String? = null, val descripcion: String, val completada: Boolean, val usuario: Usuario)","description":"com.jluqgon214.hogarmate.model.Tarea","location":"app/com.jluqgon214.hogarmate.model/-tarea/index.html","searchKeys":["Tarea","data class Tarea(val _id: String? = null, val descripcion: String, val completada: Boolean, val usuario: Usuario)","com.jluqgon214.hogarmate.model.Tarea"]},{"name":"data class TareaDTO(val _id: String?, val descripcion: String, val completada: Boolean)","description":"com.jluqgon214.hogarmate.model.DTO.TareaDTO","location":"app/com.jluqgon214.hogarmate.model.DTO/-tarea-d-t-o/index.html","searchKeys":["TareaDTO","data class TareaDTO(val _id: String?, val descripcion: String, val completada: Boolean)","com.jluqgon214.hogarmate.model.DTO.TareaDTO"]},{"name":"data class Usuario(val _id: String, val username: String, val password: String, val email: String, val roles: String, val hogar: String? = null)","description":"com.jluqgon214.hogarmate.model.Usuario","location":"app/com.jluqgon214.hogarmate.model/-usuario/index.html","searchKeys":["Usuario","data class Usuario(val _id: String, val username: String, val password: String, val email: String, val roles: String, val hogar: String? = null)","com.jluqgon214.hogarmate.model.Usuario"]},{"name":"data class UsuarioConTareasDTO(val _id: String?, val username: String, val email: String, val roles: String, val tareas: List<TareaDTO>)","description":"com.jluqgon214.hogarmate.model.DTO.UsuarioConTareasDTO","location":"app/com.jluqgon214.hogarmate.model.DTO/-usuario-con-tareas-d-t-o/index.html","searchKeys":["UsuarioConTareasDTO","data class UsuarioConTareasDTO(val _id: String?, val username: String, val email: String, val roles: String, val tareas: List<TareaDTO>)","com.jluqgon214.hogarmate.model.DTO.UsuarioConTareasDTO"]},{"name":"enum AdminNavegationBarItems : Enum<AdminNavegationBarItems> ","description":"com.jluqgon214.hogarmate.components.AdminNavegationBarItems","location":"app/com.jluqgon214.hogarmate.components/-admin-navegation-bar-items/index.html","searchKeys":["AdminNavegationBarItems","enum AdminNavegationBarItems : Enum<AdminNavegationBarItems> ","com.jluqgon214.hogarmate.components.AdminNavegationBarItems"]},{"name":"enum NavegationBarItems : Enum<NavegationBarItems> ","description":"com.jluqgon214.hogarmate.components.NavegationBarItems","location":"app/com.jluqgon214.hogarmate.components/-navegation-bar-items/index.html","searchKeys":["NavegationBarItems","enum NavegationBarItems : Enum<NavegationBarItems> ","com.jluqgon214.hogarmate.components.NavegationBarItems"]},{"name":"fun AddTaskDialog(tasksViewModel: TasksViewModel, adminViewModel: AdminViewModel?, usuario: UsuarioConTareasDTO?)","description":"com.jluqgon214.hogarmate.components.AddTaskDialog","location":"app/com.jluqgon214.hogarmate.components/-add-task-dialog.html","searchKeys":["AddTaskDialog","fun AddTaskDialog(tasksViewModel: TasksViewModel, adminViewModel: AdminViewModel?, usuario: UsuarioConTareasDTO?)","com.jluqgon214.hogarmate.components.AddTaskDialog"]},{"name":"fun AdminAnimatedBottomBar(show: Boolean, selectedIndex: Int, onItemSelected: (Int) -> Unit, onNavigate: (Int) -> Unit)","description":"com.jluqgon214.hogarmate.components.AdminAnimatedBottomBar","location":"app/com.jluqgon214.hogarmate.components/-admin-animated-bottom-bar.html","searchKeys":["AdminAnimatedBottomBar","fun AdminAnimatedBottomBar(show: Boolean, selectedIndex: Int, onItemSelected: (Int) -> Unit, onNavigate: (Int) -> Unit)","com.jluqgon214.hogarmate.components.AdminAnimatedBottomBar"]},{"name":"fun AdminScreen(adminViewModel: AdminViewModel, paddingValues: PaddingValues, tasksViewModel: TasksViewModel, profileViewModel: ProfileViewModel)","description":"com.jluqgon214.hogarmate.screens.AdminScreen","location":"app/com.jluqgon214.hogarmate.screens/-admin-screen.html","searchKeys":["AdminScreen","fun AdminScreen(adminViewModel: AdminViewModel, paddingValues: PaddingValues, tasksViewModel: TasksViewModel, profileViewModel: ProfileViewModel)","com.jluqgon214.hogarmate.screens.AdminScreen"]},{"name":"fun AlertButton(onClick: () -> Unit, text: String, textColor: Color, enabled: Boolean = true)","description":"com.jluqgon214.hogarmate.components.AlertButton","location":"app/com.jluqgon214.hogarmate.components/-alert-button.html","searchKeys":["AlertButton","fun AlertButton(onClick: () -> Unit, text: String, textColor: Color, enabled: Boolean = true)","com.jluqgon214.hogarmate.components.AlertButton"]},{"name":"fun AnimatedBottomBar(show: Boolean, selectedIndex: Int, onItemSelected: (Int) -> Unit, onNavigate: (Int) -> Unit)","description":"com.jluqgon214.hogarmate.components.AnimatedBottomBar","location":"app/com.jluqgon214.hogarmate.components/-animated-bottom-bar.html","searchKeys":["AnimatedBottomBar","fun AnimatedBottomBar(show: Boolean, selectedIndex: Int, onItemSelected: (Int) -> Unit, onNavigate: (Int) -> Unit)","com.jluqgon214.hogarmate.components.AnimatedBottomBar"]},{"name":"fun AppNavigation(themeViewModel: ThemeViewModel)","description":"com.jluqgon214.hogarmate.navigation.AppNavigation","location":"app/com.jluqgon214.hogarmate.navigation/-app-navigation.html","searchKeys":["AppNavigation","fun AppNavigation(themeViewModel: ThemeViewModel)","com.jluqgon214.hogarmate.navigation.AppNavigation"]},{"name":"fun CardTarea(task: Tarea, assignedUser: String, onComplete: () -> Unit, onDelete: () -> Unit)","description":"com.jluqgon214.hogarmate.components.CardTarea","location":"app/com.jluqgon214.hogarmate.components/-card-tarea.html","searchKeys":["CardTarea","fun CardTarea(task: Tarea, assignedUser: String, onComplete: () -> Unit, onDelete: () -> Unit)","com.jluqgon214.hogarmate.components.CardTarea"]},{"name":"fun CustomBottomBar(isAdmin: Boolean, showBottomBar: Boolean, selectedBottomBarIndex: Int, onItemSelected: (Int) -> Unit, onNavigate: (Int) -> Unit)","description":"com.jluqgon214.hogarmate.components.CustomBottomBar","location":"app/com.jluqgon214.hogarmate.components/-custom-bottom-bar.html","searchKeys":["CustomBottomBar","fun CustomBottomBar(isAdmin: Boolean, showBottomBar: Boolean, selectedBottomBarIndex: Int, onItemSelected: (Int) -> Unit, onNavigate: (Int) -> Unit)","com.jluqgon214.hogarmate.components.CustomBottomBar"]},{"name":"fun CustomButton(onClick: () -> Unit, content: () -> Unit)","description":"com.jluqgon214.hogarmate.components.CustomButton","location":"app/com.jluqgon214.hogarmate.components/-custom-button.html","searchKeys":["CustomButton","fun CustomButton(onClick: () -> Unit, content: () -> Unit)","com.jluqgon214.hogarmate.components.CustomButton"]},{"name":"fun CustomTextField(label: String, value: String, onValueChange: (String) -> Unit, placeholder: String)","description":"com.jluqgon214.hogarmate.components.CustomTextField","location":"app/com.jluqgon214.hogarmate.components/-custom-text-field.html","searchKeys":["CustomTextField","fun CustomTextField(label: String, value: String, onValueChange: (String) -> Unit, placeholder: String)","com.jluqgon214.hogarmate.components.CustomTextField"]},{"name":"fun EditProfileDialog(profileViewModel: ProfileViewModel)","description":"com.jluqgon214.hogarmate.components.EditProfileDialog","location":"app/com.jluqgon214.hogarmate.components/-edit-profile-dialog.html","searchKeys":["EditProfileDialog","fun EditProfileDialog(profileViewModel: ProfileViewModel)","com.jluqgon214.hogarmate.components.EditProfileDialog"]},{"name":"fun FAB(onFabClick: () -> Unit, show: Boolean)","description":"com.jluqgon214.hogarmate.components.FAB","location":"app/com.jluqgon214.hogarmate.components/-f-a-b.html","searchKeys":["FAB","fun FAB(onFabClick: () -> Unit, show: Boolean)","com.jluqgon214.hogarmate.components.FAB"]},{"name":"fun HogarMateTheme(darkTheme: Boolean, content: () -> Unit)","description":"com.jluqgon214.hogarmate.ui.theme.HogarMateTheme","location":"app/com.jluqgon214.hogarmate.ui.theme/-hogar-mate-theme.html","searchKeys":["HogarMateTheme","fun HogarMateTheme(darkTheme: Boolean, content: () -> Unit)","com.jluqgon214.hogarmate.ui.theme.HogarMateTheme"]},{"name":"fun HomeScreen()","description":"com.jluqgon214.hogarmate.screens.HomeScreen","location":"app/com.jluqgon214.hogarmate.screens/-home-screen.html","searchKeys":["HomeScreen","fun HomeScreen()","com.jluqgon214.hogarmate.screens.HomeScreen"]},{"name":"fun LoginScreen(loginViewModel: LoginViewModel, navController: NavController)","description":"com.jluqgon214.hogarmate.screens.LoginScreen","location":"app/com.jluqgon214.hogarmate.screens/-login-screen.html","searchKeys":["LoginScreen","fun LoginScreen(loginViewModel: LoginViewModel, navController: NavController)","com.jluqgon214.hogarmate.screens.LoginScreen"]},{"name":"fun ProfileScreen(navController: NavController, loginViewModel: LoginViewModel, AppViewModel: AppViewModel, profileViewModel: ProfileViewModel)","description":"com.jluqgon214.hogarmate.screens.ProfileScreen","location":"app/com.jluqgon214.hogarmate.screens/-profile-screen.html","searchKeys":["ProfileScreen","fun ProfileScreen(navController: NavController, loginViewModel: LoginViewModel, AppViewModel: AppViewModel, profileViewModel: ProfileViewModel)","com.jluqgon214.hogarmate.screens.ProfileScreen"]},{"name":"fun RegisterScreen(registerViewModel: RegisterViewModel, navController: NavController)","description":"com.jluqgon214.hogarmate.screens.RegisterScreen","location":"app/com.jluqgon214.hogarmate.screens/-register-screen.html","searchKeys":["RegisterScreen","fun RegisterScreen(registerViewModel: RegisterViewModel, navController: NavController)","com.jluqgon214.hogarmate.screens.RegisterScreen"]},{"name":"fun SettingsScreen(themeViewModel: ThemeViewModel, paddingValues: PaddingValues, navController: NavController, appViewModel: AppViewModel, adminViewModel: AdminViewModel)","description":"com.jluqgon214.hogarmate.screens.SettingsScreen","location":"app/com.jluqgon214.hogarmate.screens/-settings-screen.html","searchKeys":["SettingsScreen","fun SettingsScreen(themeViewModel: ThemeViewModel, paddingValues: PaddingValues, navController: NavController, appViewModel: AppViewModel, adminViewModel: AdminViewModel)","com.jluqgon214.hogarmate.screens.SettingsScreen"]},{"name":"fun TasksScreen(tasksViewModel: TasksViewModel, paddingValues: PaddingValues, navController: NavController)","description":"com.jluqgon214.hogarmate.screens.TasksScreen","location":"app/com.jluqgon214.hogarmate.screens/-tasks-screen.html","searchKeys":["TasksScreen","fun TasksScreen(tasksViewModel: TasksViewModel, paddingValues: PaddingValues, navController: NavController)","com.jluqgon214.hogarmate.screens.TasksScreen"]},{"name":"fun ThemeSwitcher(darkTheme: Boolean = false, size: Dp = 150.dp, iconSize: Dp = size / 3, padding: Dp = 10.dp, borderWidth: Dp = 1.dp, parentShape: Shape = CircleShape, toggleShape: Shape = CircleShape, animationSpec: AnimationSpec<Dp> = tween(durationMillis = 300), onClick: () -> Unit)","description":"com.jluqgon214.hogarmate.components.ThemeSwitcher","location":"app/com.jluqgon214.hogarmate.components/-theme-switcher.html","searchKeys":["ThemeSwitcher","fun ThemeSwitcher(darkTheme: Boolean = false, size: Dp = 150.dp, iconSize: Dp = size / 3, padding: Dp = 10.dp, borderWidth: Dp = 1.dp, parentShape: Shape = CircleShape, toggleShape: Shape = CircleShape, animationSpec: AnimationSpec<Dp> = tween(durationMillis = 300), onClick: () -> Unit)","com.jluqgon214.hogarmate.components.ThemeSwitcher"]},{"name":"fun TopTittle(texto: String)","description":"com.jluqgon214.hogarmate.components.TopTittle","location":"app/com.jluqgon214.hogarmate.components/-top-tittle.html","searchKeys":["TopTittle","fun TopTittle(texto: String)","com.jluqgon214.hogarmate.components.TopTittle"]},{"name":"fun UsuarioItem(usuario: UsuarioConTareasDTO, tasksViewModel: TasksViewModel, adminViewModel: AdminViewModel)","description":"com.jluqgon214.hogarmate.components.UsuarioItem","location":"app/com.jluqgon214.hogarmate.components/-usuario-item.html","searchKeys":["UsuarioItem","fun UsuarioItem(usuario: UsuarioConTareasDTO, tasksViewModel: TasksViewModel, adminViewModel: AdminViewModel)","com.jluqgon214.hogarmate.components.UsuarioItem"]},{"name":"fun actualizarEstadoTarea(id: String?)","description":"com.jluqgon214.hogarmate.viewModel.TasksViewModel.actualizarEstadoTarea","location":"app/com.jluqgon214.hogarmate.viewModel/-tasks-view-model/actualizar-estado-tarea.html","searchKeys":["actualizarEstadoTarea","fun actualizarEstadoTarea(id: String?)","com.jluqgon214.hogarmate.viewModel.TasksViewModel.actualizarEstadoTarea"]},{"name":"fun actualizarUsuario()","description":"com.jluqgon214.hogarmate.viewModel.ProfileViewModel.actualizarUsuario","location":"app/com.jluqgon214.hogarmate.viewModel/-profile-view-model/actualizar-usuario.html","searchKeys":["actualizarUsuario","fun actualizarUsuario()","com.jluqgon214.hogarmate.viewModel.ProfileViewModel.actualizarUsuario"]},{"name":"fun agregarTarea()","description":"com.jluqgon214.hogarmate.viewModel.TasksViewModel.agregarTarea","location":"app/com.jluqgon214.hogarmate.viewModel/-tasks-view-model/agregar-tarea.html","searchKeys":["agregarTarea","fun agregarTarea()","com.jluqgon214.hogarmate.viewModel.TasksViewModel.agregarTarea"]},{"name":"fun agregarTareaUsuario(idUsuario: String?)","description":"com.jluqgon214.hogarmate.viewModel.TasksViewModel.agregarTareaUsuario","location":"app/com.jluqgon214.hogarmate.viewModel/-tasks-view-model/agregar-tarea-usuario.html","searchKeys":["agregarTareaUsuario","fun agregarTareaUsuario(idUsuario: String?)","com.jluqgon214.hogarmate.viewModel.TasksViewModel.agregarTareaUsuario"]},{"name":"fun comprobarAdmin()","description":"com.jluqgon214.hogarmate.viewModel.AdminViewModel.comprobarAdmin","location":"app/com.jluqgon214.hogarmate.viewModel/-admin-view-model/comprobar-admin.html","searchKeys":["comprobarAdmin","fun comprobarAdmin()","com.jluqgon214.hogarmate.viewModel.AdminViewModel.comprobarAdmin"]},{"name":"fun eliminarTarea(id: String?)","description":"com.jluqgon214.hogarmate.viewModel.TasksViewModel.eliminarTarea","location":"app/com.jluqgon214.hogarmate.viewModel/-tasks-view-model/eliminar-tarea.html","searchKeys":["eliminarTarea","fun eliminarTarea(id: String?)","com.jluqgon214.hogarmate.viewModel.TasksViewModel.eliminarTarea"]},{"name":"fun filtrarTareas()","description":"com.jluqgon214.hogarmate.viewModel.TasksViewModel.filtrarTareas","location":"app/com.jluqgon214.hogarmate.viewModel/-tasks-view-model/filtrar-tareas.html","searchKeys":["filtrarTareas","fun filtrarTareas()","com.jluqgon214.hogarmate.viewModel.TasksViewModel.filtrarTareas"]},{"name":"fun getJWT(): String?","description":"com.jluqgon214.hogarmate.viewModel.LoginViewModel.Companion.getJWT","location":"app/com.jluqgon214.hogarmate.viewModel/-login-view-model/-companion/get-j-w-t.html","searchKeys":["getJWT","fun getJWT(): String?","com.jluqgon214.hogarmate.viewModel.LoginViewModel.Companion.getJWT"]},{"name":"fun isFormValid(): Boolean","description":"com.jluqgon214.hogarmate.viewModel.ProfileViewModel.isFormValid","location":"app/com.jluqgon214.hogarmate.viewModel/-profile-view-model/is-form-valid.html","searchKeys":["isFormValid","fun isFormValid(): Boolean","com.jluqgon214.hogarmate.viewModel.ProfileViewModel.isFormValid"]},{"name":"fun login()","description":"com.jluqgon214.hogarmate.viewModel.LoginViewModel.login","location":"app/com.jluqgon214.hogarmate.viewModel/-login-view-model/login.html","searchKeys":["login","fun login()","com.jluqgon214.hogarmate.viewModel.LoginViewModel.login"]},{"name":"fun obtenerTareas()","description":"com.jluqgon214.hogarmate.viewModel.TasksViewModel.obtenerTareas","location":"app/com.jluqgon214.hogarmate.viewModel/-tasks-view-model/obtener-tareas.html","searchKeys":["obtenerTareas","fun obtenerTareas()","com.jluqgon214.hogarmate.viewModel.TasksViewModel.obtenerTareas"]},{"name":"fun obtenerUsuario()","description":"com.jluqgon214.hogarmate.viewModel.ProfileViewModel.obtenerUsuario","location":"app/com.jluqgon214.hogarmate.viewModel/-profile-view-model/obtener-usuario.html","searchKeys":["obtenerUsuario","fun obtenerUsuario()","com.jluqgon214.hogarmate.viewModel.ProfileViewModel.obtenerUsuario"]},{"name":"fun obtenerUsuariosConTareas()","description":"com.jluqgon214.hogarmate.viewModel.AdminViewModel.obtenerUsuariosConTareas","location":"app/com.jluqgon214.hogarmate.viewModel/-admin-view-model/obtener-usuarios-con-tareas.html","searchKeys":["obtenerUsuariosConTareas","fun obtenerUsuariosConTareas()","com.jluqgon214.hogarmate.viewModel.AdminViewModel.obtenerUsuariosConTareas"]},{"name":"fun register()","description":"com.jluqgon214.hogarmate.viewModel.RegisterViewModel.register","location":"app/com.jluqgon214.hogarmate.viewModel/-register-view-model/register.html","searchKeys":["register","fun register()","com.jluqgon214.hogarmate.viewModel.RegisterViewModel.register"]},{"name":"fun setAdminDialog(show: Boolean)","description":"com.jluqgon214.hogarmate.viewModel.TasksViewModel.setAdminDialog","location":"app/com.jluqgon214.hogarmate.viewModel/-tasks-view-model/set-admin-dialog.html","searchKeys":["setAdminDialog","fun setAdminDialog(show: Boolean)","com.jluqgon214.hogarmate.viewModel.TasksViewModel.setAdminDialog"]},{"name":"fun setDescription(description: String)","description":"com.jluqgon214.hogarmate.viewModel.TasksViewModel.setDescription","location":"app/com.jluqgon214.hogarmate.viewModel/-tasks-view-model/set-description.html","searchKeys":["setDescription","fun setDescription(description: String)","com.jluqgon214.hogarmate.viewModel.TasksViewModel.setDescription"]},{"name":"fun setEmail(email: String)","description":"com.jluqgon214.hogarmate.viewModel.LoginViewModel.setEmail","location":"app/com.jluqgon214.hogarmate.viewModel/-login-view-model/set-email.html","searchKeys":["setEmail","fun setEmail(email: String)","com.jluqgon214.hogarmate.viewModel.LoginViewModel.setEmail"]},{"name":"fun setEmail(email: String)","description":"com.jluqgon214.hogarmate.viewModel.RegisterViewModel.setEmail","location":"app/com.jluqgon214.hogarmate.viewModel/-register-view-model/set-email.html","searchKeys":["setEmail","fun setEmail(email: String)","com.jluqgon214.hogarmate.viewModel.RegisterViewModel.setEmail"]},{"name":"fun setEmail(value: String)","description":"com.jluqgon214.hogarmate.viewModel.ProfileViewModel.setEmail","location":"app/com.jluqgon214.hogarmate.viewModel/-profile-view-model/set-email.html","searchKeys":["setEmail","fun setEmail(value: String)","com.jluqgon214.hogarmate.viewModel.ProfileViewModel.setEmail"]},{"name":"fun setErrorMessage(message: String?)","description":"com.jluqgon214.hogarmate.viewModel.LoginViewModel.setErrorMessage","location":"app/com.jluqgon214.hogarmate.viewModel/-login-view-model/set-error-message.html","searchKeys":["setErrorMessage","fun setErrorMessage(message: String?)","com.jluqgon214.hogarmate.viewModel.LoginViewModel.setErrorMessage"]},{"name":"fun setJWT(jwt: String?)","description":"com.jluqgon214.hogarmate.viewModel.LoginViewModel.setJWT","location":"app/com.jluqgon214.hogarmate.viewModel/-login-view-model/set-j-w-t.html","searchKeys":["setJWT","fun setJWT(jwt: String?)","com.jluqgon214.hogarmate.viewModel.LoginViewModel.setJWT"]},{"name":"fun setLoginCorrecto(value: Boolean)","description":"com.jluqgon214.hogarmate.viewModel.LoginViewModel.setLoginCorrecto","location":"app/com.jluqgon214.hogarmate.viewModel/-login-view-model/set-login-correcto.html","searchKeys":["setLoginCorrecto","fun setLoginCorrecto(value: Boolean)","com.jluqgon214.hogarmate.viewModel.LoginViewModel.setLoginCorrecto"]},{"name":"fun setPassword(password: String)","description":"com.jluqgon214.hogarmate.viewModel.LoginViewModel.setPassword","location":"app/com.jluqgon214.hogarmate.viewModel/-login-view-model/set-password.html","searchKeys":["setPassword","fun setPassword(password: String)","com.jluqgon214.hogarmate.viewModel.LoginViewModel.setPassword"]},{"name":"fun setPassword(password: String)","description":"com.jluqgon214.hogarmate.viewModel.RegisterViewModel.setPassword","location":"app/com.jluqgon214.hogarmate.viewModel/-register-view-model/set-password.html","searchKeys":["setPassword","fun setPassword(password: String)","com.jluqgon214.hogarmate.viewModel.RegisterViewModel.setPassword"]},{"name":"fun setRepeatPassword(password: String)","description":"com.jluqgon214.hogarmate.viewModel.RegisterViewModel.setRepeatPassword","location":"app/com.jluqgon214.hogarmate.viewModel/-register-view-model/set-repeat-password.html","searchKeys":["setRepeatPassword","fun setRepeatPassword(password: String)","com.jluqgon214.hogarmate.viewModel.RegisterViewModel.setRepeatPassword"]},{"name":"fun setSelectedBottomBarIndex(index: Int)","description":"com.jluqgon214.hogarmate.viewModel.AppViewModel.setSelectedBottomBarIndex","location":"app/com.jluqgon214.hogarmate.viewModel/-app-view-model/set-selected-bottom-bar-index.html","searchKeys":["setSelectedBottomBarIndex","fun setSelectedBottomBarIndex(index: Int)","com.jluqgon214.hogarmate.viewModel.AppViewModel.setSelectedBottomBarIndex"]},{"name":"fun setShowBottomBar(show: Boolean)","description":"com.jluqgon214.hogarmate.viewModel.AppViewModel.setShowBottomBar","location":"app/com.jluqgon214.hogarmate.viewModel/-app-view-model/set-show-bottom-bar.html","searchKeys":["setShowBottomBar","fun setShowBottomBar(show: Boolean)","com.jluqgon214.hogarmate.viewModel.AppViewModel.setShowBottomBar"]},{"name":"fun setShowDialog(show: Boolean)","description":"com.jluqgon214.hogarmate.viewModel.TasksViewModel.setShowDialog","location":"app/com.jluqgon214.hogarmate.viewModel/-tasks-view-model/set-show-dialog.html","searchKeys":["setShowDialog","fun setShowDialog(show: Boolean)","com.jluqgon214.hogarmate.viewModel.TasksViewModel.setShowDialog"]},{"name":"fun setShowEditDialog(value: Boolean)","description":"com.jluqgon214.hogarmate.viewModel.ProfileViewModel.setShowEditDialog","location":"app/com.jluqgon214.hogarmate.viewModel/-profile-view-model/set-show-edit-dialog.html","searchKeys":["setShowEditDialog","fun setShowEditDialog(value: Boolean)","com.jluqgon214.hogarmate.viewModel.ProfileViewModel.setShowEditDialog"]},{"name":"fun setShowFAB(show: Boolean)","description":"com.jluqgon214.hogarmate.viewModel.AppViewModel.setShowFAB","location":"app/com.jluqgon214.hogarmate.viewModel/-app-view-model/set-show-f-a-b.html","searchKeys":["setShowFAB","fun setShowFAB(show: Boolean)","com.jluqgon214.hogarmate.viewModel.AppViewModel.setShowFAB"]},{"name":"fun setTextoTop(texto: String)","description":"com.jluqgon214.hogarmate.viewModel.AppViewModel.setTextoTop","location":"app/com.jluqgon214.hogarmate.viewModel/-app-view-model/set-texto-top.html","searchKeys":["setTextoTop","fun setTextoTop(texto: String)","com.jluqgon214.hogarmate.viewModel.AppViewModel.setTextoTop"]},{"name":"fun setUsername(username: String)","description":"com.jluqgon214.hogarmate.viewModel.RegisterViewModel.setUsername","location":"app/com.jluqgon214.hogarmate.viewModel/-register-view-model/set-username.html","searchKeys":["setUsername","fun setUsername(username: String)","com.jluqgon214.hogarmate.viewModel.RegisterViewModel.setUsername"]},{"name":"fun setUsername(value: String)","description":"com.jluqgon214.hogarmate.viewModel.ProfileViewModel.setUsername","location":"app/com.jluqgon214.hogarmate.viewModel/-profile-view-model/set-username.html","searchKeys":["setUsername","fun setUsername(value: String)","com.jluqgon214.hogarmate.viewModel.ProfileViewModel.setUsername"]},{"name":"fun setUsuario(usuario: UsuarioConTareasDTO)","description":"com.jluqgon214.hogarmate.viewModel.TasksViewModel.setUsuario","location":"app/com.jluqgon214.hogarmate.viewModel/-tasks-view-model/set-usuario.html","searchKeys":["setUsuario","fun setUsuario(usuario: UsuarioConTareasDTO)","com.jluqgon214.hogarmate.viewModel.TasksViewModel.setUsuario"]},{"name":"fun setUsuarioActualId(id: String)","description":"com.jluqgon214.hogarmate.viewModel.AdminViewModel.setUsuarioActualId","location":"app/com.jluqgon214.hogarmate.viewModel/-admin-view-model/set-usuario-actual-id.html","searchKeys":["setUsuarioActualId","fun setUsuarioActualId(id: String)","com.jluqgon214.hogarmate.viewModel.AdminViewModel.setUsuarioActualId"]},{"name":"fun toggleTheme()","description":"com.jluqgon214.hogarmate.viewModel.ThemeViewModel.toggleTheme","location":"app/com.jluqgon214.hogarmate.viewModel/-theme-view-model/toggle-theme.html","searchKeys":["toggleTheme","fun toggleTheme()","com.jluqgon214.hogarmate.viewModel.ThemeViewModel.toggleTheme"]},{"name":"fun valueOf(value: String): AdminNavegationBarItems","description":"com.jluqgon214.hogarmate.components.AdminNavegationBarItems.valueOf","location":"app/com.jluqgon214.hogarmate.components/-admin-navegation-bar-items/value-of.html","searchKeys":["valueOf","fun valueOf(value: String): AdminNavegationBarItems","com.jluqgon214.hogarmate.components.AdminNavegationBarItems.valueOf"]},{"name":"fun valueOf(value: String): NavegationBarItems","description":"com.jluqgon214.hogarmate.components.NavegationBarItems.valueOf","location":"app/com.jluqgon214.hogarmate.components/-navegation-bar-items/value-of.html","searchKeys":["valueOf","fun valueOf(value: String): NavegationBarItems","com.jluqgon214.hogarmate.components.NavegationBarItems.valueOf"]},{"name":"fun values(): Array<AdminNavegationBarItems>","description":"com.jluqgon214.hogarmate.components.AdminNavegationBarItems.values","location":"app/com.jluqgon214.hogarmate.components/-admin-navegation-bar-items/values.html","searchKeys":["values","fun values(): Array<AdminNavegationBarItems>","com.jluqgon214.hogarmate.components.AdminNavegationBarItems.values"]},{"name":"fun values(): Array<NavegationBarItems>","description":"com.jluqgon214.hogarmate.components.NavegationBarItems.values","location":"app/com.jluqgon214.hogarmate.components/-navegation-bar-items/values.html","searchKeys":["values","fun values(): Array<NavegationBarItems>","com.jluqgon214.hogarmate.components.NavegationBarItems.values"]},{"name":"interface ApiService","description":"com.jluqgon214.hogarmate.service.ApiService","location":"app/com.jluqgon214.hogarmate.service/-api-service/index.html","searchKeys":["ApiService","interface ApiService","com.jluqgon214.hogarmate.service.ApiService"]},{"name":"object Companion","description":"com.jluqgon214.hogarmate.viewModel.LoginViewModel.Companion","location":"app/com.jluqgon214.hogarmate.viewModel/-login-view-model/-companion/index.html","searchKeys":["Companion","object Companion","com.jluqgon214.hogarmate.viewModel.LoginViewModel.Companion"]},{"name":"object RetrofitClient","description":"com.jluqgon214.hogarmate.client.RetrofitClient","location":"app/com.jluqgon214.hogarmate.client/-retrofit-client/index.html","searchKeys":["RetrofitClient","object RetrofitClient","com.jluqgon214.hogarmate.client.RetrofitClient"]},{"name":"open override fun intercept(chain: Interceptor.Chain): Response","description":"com.jluqgon214.hogarmate.client.AuthInterceptor.intercept","location":"app/com.jluqgon214.hogarmate.client/-auth-interceptor/intercept.html","searchKeys":["intercept","open override fun intercept(chain: Interceptor.Chain): Response","com.jluqgon214.hogarmate.client.AuthInterceptor.intercept"]},{"name":"suspend fun login(username: String, password: String): Response<LoginResponse>","description":"com.jluqgon214.hogarmate.repository.LoginRepository.login","location":"app/com.jluqgon214.hogarmate.repository/-login-repository/login.html","searchKeys":["login","suspend fun login(username: String, password: String): Response<LoginResponse>","com.jluqgon214.hogarmate.repository.LoginRepository.login"]},{"name":"suspend fun register(username: String, email: String, password: String, passwordRepeat: String, rol: String = \"USER\", hogar: String? = null): Response<RegisterResponse>","description":"com.jluqgon214.hogarmate.repository.RegisterRepository.register","location":"app/com.jluqgon214.hogarmate.repository/-register-repository/register.html","searchKeys":["register","suspend fun register(username: String, email: String, password: String, passwordRepeat: String, rol: String = \"USER\", hogar: String? = null): Response<RegisterResponse>","com.jluqgon214.hogarmate.repository.RegisterRepository.register"]},{"name":"suspend fun saveTheme(isDark: Boolean)","description":"com.jluqgon214.hogarmate.preferences.ThemePreferences.saveTheme","location":"app/com.jluqgon214.hogarmate.preferences/-theme-preferences/save-theme.html","searchKeys":["saveTheme","suspend fun saveTheme(isDark: Boolean)","com.jluqgon214.hogarmate.preferences.ThemePreferences.saveTheme"]},{"name":"val AppTypography: Typography","description":"com.jluqgon214.hogarmate.ui.theme.AppTypography","location":"app/com.jluqgon214.hogarmate.ui.theme/-app-typography.html","searchKeys":["AppTypography","val AppTypography: Typography","com.jluqgon214.hogarmate.ui.theme.AppTypography"]},{"name":"val JWT: StateFlow<String?>","description":"com.jluqgon214.hogarmate.viewModel.LoginViewModel.Companion.JWT","location":"app/com.jluqgon214.hogarmate.viewModel/-login-view-model/-companion/-j-w-t.html","searchKeys":["JWT","val JWT: StateFlow<String?>","com.jluqgon214.hogarmate.viewModel.LoginViewModel.Companion.JWT"]},{"name":"val _id: String","description":"com.jluqgon214.hogarmate.model.Usuario._id","location":"app/com.jluqgon214.hogarmate.model/-usuario/_id.html","searchKeys":["_id","val _id: String","com.jluqgon214.hogarmate.model.Usuario._id"]},{"name":"val _id: String?","description":"com.jluqgon214.hogarmate.model.DTO.TareaDTO._id","location":"app/com.jluqgon214.hogarmate.model.DTO/-tarea-d-t-o/_id.html","searchKeys":["_id","val _id: String?","com.jluqgon214.hogarmate.model.DTO.TareaDTO._id"]},{"name":"val _id: String?","description":"com.jluqgon214.hogarmate.model.DTO.UsuarioConTareasDTO._id","location":"app/com.jluqgon214.hogarmate.model.DTO/-usuario-con-tareas-d-t-o/_id.html","searchKeys":["_id","val _id: String?","com.jluqgon214.hogarmate.model.DTO.UsuarioConTareasDTO._id"]},{"name":"val _id: String? = null","description":"com.jluqgon214.hogarmate.model.Tarea._id","location":"app/com.jluqgon214.hogarmate.model/-tarea/_id.html","searchKeys":["_id","val _id: String? = null","com.jluqgon214.hogarmate.model.Tarea._id"]},{"name":"val adminDialog: StateFlow<Boolean>","description":"com.jluqgon214.hogarmate.viewModel.TasksViewModel.adminDialog","location":"app/com.jluqgon214.hogarmate.viewModel/-tasks-view-model/admin-dialog.html","searchKeys":["adminDialog","val adminDialog: StateFlow<Boolean>","com.jluqgon214.hogarmate.viewModel.TasksViewModel.adminDialog"]},{"name":"val backgroundDark: Color","description":"com.jluqgon214.hogarmate.ui.theme.backgroundDark","location":"app/com.jluqgon214.hogarmate.ui.theme/background-dark.html","searchKeys":["backgroundDark","val backgroundDark: Color","com.jluqgon214.hogarmate.ui.theme.backgroundDark"]},{"name":"val backgroundLight: Color","description":"com.jluqgon214.hogarmate.ui.theme.backgroundLight","location":"app/com.jluqgon214.hogarmate.ui.theme/background-light.html","searchKeys":["backgroundLight","val backgroundLight: Color","com.jluqgon214.hogarmate.ui.theme.backgroundLight"]},{"name":"val baseline: Typography","description":"com.jluqgon214.hogarmate.ui.theme.baseline","location":"app/com.jluqgon214.hogarmate.ui.theme/baseline.html","searchKeys":["baseline","val baseline: Typography","com.jluqgon214.hogarmate.ui.theme.baseline"]},{"name":"val bodyFontFamily: FontFamily","description":"com.jluqgon214.hogarmate.ui.theme.bodyFontFamily","location":"app/com.jluqgon214.hogarmate.ui.theme/body-font-family.html","searchKeys":["bodyFontFamily","val bodyFontFamily: FontFamily","com.jluqgon214.hogarmate.ui.theme.bodyFontFamily"]},{"name":"val completada: Boolean","description":"com.jluqgon214.hogarmate.model.DTO.TareaDTO.completada","location":"app/com.jluqgon214.hogarmate.model.DTO/-tarea-d-t-o/completada.html","searchKeys":["completada","val completada: Boolean","com.jluqgon214.hogarmate.model.DTO.TareaDTO.completada"]},{"name":"val completada: Boolean","description":"com.jluqgon214.hogarmate.model.Tarea.completada","location":"app/com.jluqgon214.hogarmate.model/-tarea/completada.html","searchKeys":["completada","val completada: Boolean","com.jluqgon214.hogarmate.model.Tarea.completada"]},{"name":"val descripcion: String","description":"com.jluqgon214.hogarmate.model.DTO.CrearTareaDTO.descripcion","location":"app/com.jluqgon214.hogarmate.model.DTO/-crear-tarea-d-t-o/descripcion.html","searchKeys":["descripcion","val descripcion: String","com.jluqgon214.hogarmate.model.DTO.CrearTareaDTO.descripcion"]},{"name":"val descripcion: String","description":"com.jluqgon214.hogarmate.model.DTO.TareaDTO.descripcion","location":"app/com.jluqgon214.hogarmate.model.DTO/-tarea-d-t-o/descripcion.html","searchKeys":["descripcion","val descripcion: String","com.jluqgon214.hogarmate.model.DTO.TareaDTO.descripcion"]},{"name":"val descripcion: String","description":"com.jluqgon214.hogarmate.model.Tarea.descripcion","location":"app/com.jluqgon214.hogarmate.model/-tarea/descripcion.html","searchKeys":["descripcion","val descripcion: String","com.jluqgon214.hogarmate.model.Tarea.descripcion"]},{"name":"val description: StateFlow<String>","description":"com.jluqgon214.hogarmate.viewModel.TasksViewModel.description","location":"app/com.jluqgon214.hogarmate.viewModel/-tasks-view-model/description.html","searchKeys":["description","val description: StateFlow<String>","com.jluqgon214.hogarmate.viewModel.TasksViewModel.description"]},{"name":"val displayFontFamily: FontFamily","description":"com.jluqgon214.hogarmate.ui.theme.displayFontFamily","location":"app/com.jluqgon214.hogarmate.ui.theme/display-font-family.html","searchKeys":["displayFontFamily","val displayFontFamily: FontFamily","com.jluqgon214.hogarmate.ui.theme.displayFontFamily"]},{"name":"val email: StateFlow<String>","description":"com.jluqgon214.hogarmate.viewModel.LoginViewModel.email","location":"app/com.jluqgon214.hogarmate.viewModel/-login-view-model/email.html","searchKeys":["email","val email: StateFlow<String>","com.jluqgon214.hogarmate.viewModel.LoginViewModel.email"]},{"name":"val email: StateFlow<String>","description":"com.jluqgon214.hogarmate.viewModel.ProfileViewModel.email","location":"app/com.jluqgon214.hogarmate.viewModel/-profile-view-model/email.html","searchKeys":["email","val email: StateFlow<String>","com.jluqgon214.hogarmate.viewModel.ProfileViewModel.email"]},{"name":"val email: StateFlow<String>","description":"com.jluqgon214.hogarmate.viewModel.RegisterViewModel.email","location":"app/com.jluqgon214.hogarmate.viewModel/-register-view-model/email.html","searchKeys":["email","val email: StateFlow<String>","com.jluqgon214.hogarmate.viewModel.RegisterViewModel.email"]},{"name":"val email: String","description":"com.jluqgon214.hogarmate.model.DTO.UsuarioConTareasDTO.email","location":"app/com.jluqgon214.hogarmate.model.DTO/-usuario-con-tareas-d-t-o/email.html","searchKeys":["email","val email: String","com.jluqgon214.hogarmate.model.DTO.UsuarioConTareasDTO.email"]},{"name":"val email: String","description":"com.jluqgon214.hogarmate.model.LoginRequest.email","location":"app/com.jluqgon214.hogarmate.model/-login-request/email.html","searchKeys":["email","val email: String","com.jluqgon214.hogarmate.model.LoginRequest.email"]},{"name":"val email: String","description":"com.jluqgon214.hogarmate.model.RegisterRequest.email","location":"app/com.jluqgon214.hogarmate.model/-register-request/email.html","searchKeys":["email","val email: String","com.jluqgon214.hogarmate.model.RegisterRequest.email"]},{"name":"val email: String","description":"com.jluqgon214.hogarmate.model.Usuario.email","location":"app/com.jluqgon214.hogarmate.model/-usuario/email.html","searchKeys":["email","val email: String","com.jluqgon214.hogarmate.model.Usuario.email"]},{"name":"val errorContainerDark: Color","description":"com.jluqgon214.hogarmate.ui.theme.errorContainerDark","location":"app/com.jluqgon214.hogarmate.ui.theme/error-container-dark.html","searchKeys":["errorContainerDark","val errorContainerDark: Color","com.jluqgon214.hogarmate.ui.theme.errorContainerDark"]},{"name":"val errorContainerLight: Color","description":"com.jluqgon214.hogarmate.ui.theme.errorContainerLight","location":"app/com.jluqgon214.hogarmate.ui.theme/error-container-light.html","searchKeys":["errorContainerLight","val errorContainerLight: Color","com.jluqgon214.hogarmate.ui.theme.errorContainerLight"]},{"name":"val errorDark: Color","description":"com.jluqgon214.hogarmate.ui.theme.errorDark","location":"app/com.jluqgon214.hogarmate.ui.theme/error-dark.html","searchKeys":["errorDark","val errorDark: Color","com.jluqgon214.hogarmate.ui.theme.errorDark"]},{"name":"val errorLight: Color","description":"com.jluqgon214.hogarmate.ui.theme.errorLight","location":"app/com.jluqgon214.hogarmate.ui.theme/error-light.html","searchKeys":["errorLight","val errorLight: Color","com.jluqgon214.hogarmate.ui.theme.errorLight"]},{"name":"val errorMessage: StateFlow<String?>","description":"com.jluqgon214.hogarmate.viewModel.LoginViewModel.errorMessage","location":"app/com.jluqgon214.hogarmate.viewModel/-login-view-model/error-message.html","searchKeys":["errorMessage","val errorMessage: StateFlow<String?>","com.jluqgon214.hogarmate.viewModel.LoginViewModel.errorMessage"]},{"name":"val errorMessage: StateFlow<String?>","description":"com.jluqgon214.hogarmate.viewModel.ProfileViewModel.errorMessage","location":"app/com.jluqgon214.hogarmate.viewModel/-profile-view-model/error-message.html","searchKeys":["errorMessage","val errorMessage: StateFlow<String?>","com.jluqgon214.hogarmate.viewModel.ProfileViewModel.errorMessage"]},{"name":"val errorMessage: StateFlow<String?>","description":"com.jluqgon214.hogarmate.viewModel.RegisterViewModel.errorMessage","location":"app/com.jluqgon214.hogarmate.viewModel/-register-view-model/error-message.html","searchKeys":["errorMessage","val errorMessage: StateFlow<String?>","com.jluqgon214.hogarmate.viewModel.RegisterViewModel.errorMessage"]},{"name":"val hogar: String? = null","description":"com.jluqgon214.hogarmate.model.RegisterRequest.hogar","location":"app/com.jluqgon214.hogarmate.model/-register-request/hogar.html","searchKeys":["hogar","val hogar: String? = null","com.jluqgon214.hogarmate.model.RegisterRequest.hogar"]},{"name":"val hogar: String? = null","description":"com.jluqgon214.hogarmate.model.Usuario.hogar","location":"app/com.jluqgon214.hogarmate.model/-usuario/hogar.html","searchKeys":["hogar","val hogar: String? = null","com.jluqgon214.hogarmate.model.Usuario.hogar"]},{"name":"val icon: ImageVector","description":"com.jluqgon214.hogarmate.components.AdminNavegationBarItems.icon","location":"app/com.jluqgon214.hogarmate.components/-admin-navegation-bar-items/icon.html","searchKeys":["icon","val icon: ImageVector","com.jluqgon214.hogarmate.components.AdminNavegationBarItems.icon"]},{"name":"val icon: ImageVector","description":"com.jluqgon214.hogarmate.components.NavegationBarItems.icon","location":"app/com.jluqgon214.hogarmate.components/-navegation-bar-items/icon.html","searchKeys":["icon","val icon: ImageVector","com.jluqgon214.hogarmate.components.NavegationBarItems.icon"]},{"name":"val idUsuarioActual: MutableStateFlow<String?>","description":"com.jluqgon214.hogarmate.viewModel.AdminViewModel.idUsuarioActual","location":"app/com.jluqgon214.hogarmate.viewModel/-admin-view-model/id-usuario-actual.html","searchKeys":["idUsuarioActual","val idUsuarioActual: MutableStateFlow<String?>","com.jluqgon214.hogarmate.viewModel.AdminViewModel.idUsuarioActual"]},{"name":"val instance: ApiService","description":"com.jluqgon214.hogarmate.client.RetrofitClient.instance","location":"app/com.jluqgon214.hogarmate.client/-retrofit-client/instance.html","searchKeys":["instance","val instance: ApiService","com.jluqgon214.hogarmate.client.RetrofitClient.instance"]},{"name":"val inverseOnSurfaceDark: Color","description":"com.jluqgon214.hogarmate.ui.theme.inverseOnSurfaceDark","location":"app/com.jluqgon214.hogarmate.ui.theme/inverse-on-surface-dark.html","searchKeys":["inverseOnSurfaceDark","val inverseOnSurfaceDark: Color","com.jluqgon214.hogarmate.ui.theme.inverseOnSurfaceDark"]},{"name":"val inverseOnSurfaceLight: Color","description":"com.jluqgon214.hogarmate.ui.theme.inverseOnSurfaceLight","location":"app/com.jluqgon214.hogarmate.ui.theme/inverse-on-surface-light.html","searchKeys":["inverseOnSurfaceLight","val inverseOnSurfaceLight: Color","com.jluqgon214.hogarmate.ui.theme.inverseOnSurfaceLight"]},{"name":"val inversePrimaryDark: Color","description":"com.jluqgon214.hogarmate.ui.theme.inversePrimaryDark","location":"app/com.jluqgon214.hogarmate.ui.theme/inverse-primary-dark.html","searchKeys":["inversePrimaryDark","val inversePrimaryDark: Color","com.jluqgon214.hogarmate.ui.theme.inversePrimaryDark"]},{"name":"val inversePrimaryLight: Color","description":"com.jluqgon214.hogarmate.ui.theme.inversePrimaryLight","location":"app/com.jluqgon214.hogarmate.ui.theme/inverse-primary-light.html","searchKeys":["inversePrimaryLight","val inversePrimaryLight: Color","com.jluqgon214.hogarmate.ui.theme.inversePrimaryLight"]},{"name":"val inverseSurfaceDark: Color","description":"com.jluqgon214.hogarmate.ui.theme.inverseSurfaceDark","location":"app/com.jluqgon214.hogarmate.ui.theme/inverse-surface-dark.html","searchKeys":["inverseSurfaceDark","val inverseSurfaceDark: Color","com.jluqgon214.hogarmate.ui.theme.inverseSurfaceDark"]},{"name":"val inverseSurfaceLight: Color","description":"com.jluqgon214.hogarmate.ui.theme.inverseSurfaceLight","location":"app/com.jluqgon214.hogarmate.ui.theme/inverse-surface-light.html","searchKeys":["inverseSurfaceLight","val inverseSurfaceLight: Color","com.jluqgon214.hogarmate.ui.theme.inverseSurfaceLight"]},{"name":"val isAdmin: StateFlow<Boolean>","description":"com.jluqgon214.hogarmate.viewModel.AdminViewModel.isAdmin","location":"app/com.jluqgon214.hogarmate.viewModel/-admin-view-model/is-admin.html","searchKeys":["isAdmin","val isAdmin: StateFlow<Boolean>","com.jluqgon214.hogarmate.viewModel.AdminViewModel.isAdmin"]},{"name":"val isDarkTheme: Flow<Boolean>","description":"com.jluqgon214.hogarmate.preferences.ThemePreferences.isDarkTheme","location":"app/com.jluqgon214.hogarmate.preferences/-theme-preferences/is-dark-theme.html","searchKeys":["isDarkTheme","val isDarkTheme: Flow<Boolean>","com.jluqgon214.hogarmate.preferences.ThemePreferences.isDarkTheme"]},{"name":"val isDarkTheme: StateFlow<Boolean>","description":"com.jluqgon214.hogarmate.viewModel.ThemeViewModel.isDarkTheme","location":"app/com.jluqgon214.hogarmate.viewModel/-theme-view-model/is-dark-theme.html","searchKeys":["isDarkTheme","val isDarkTheme: StateFlow<Boolean>","com.jluqgon214.hogarmate.viewModel.ThemeViewModel.isDarkTheme"]},{"name":"val isLoading: StateFlow<Boolean>","description":"com.jluqgon214.hogarmate.viewModel.LoginViewModel.isLoading","location":"app/com.jluqgon214.hogarmate.viewModel/-login-view-model/is-loading.html","searchKeys":["isLoading","val isLoading: StateFlow<Boolean>","com.jluqgon214.hogarmate.viewModel.LoginViewModel.isLoading"]},{"name":"val loginCorrecto: StateFlow<Boolean>","description":"com.jluqgon214.hogarmate.viewModel.LoginViewModel.loginCorrecto","location":"app/com.jluqgon214.hogarmate.viewModel/-login-view-model/login-correcto.html","searchKeys":["loginCorrecto","val loginCorrecto: StateFlow<Boolean>","com.jluqgon214.hogarmate.viewModel.LoginViewModel.loginCorrecto"]},{"name":"val loginResponse: StateFlow<LoginResponse?>","description":"com.jluqgon214.hogarmate.viewModel.LoginViewModel.loginResponse","location":"app/com.jluqgon214.hogarmate.viewModel/-login-view-model/login-response.html","searchKeys":["loginResponse","val loginResponse: StateFlow<LoginResponse?>","com.jluqgon214.hogarmate.viewModel.LoginViewModel.loginResponse"]},{"name":"val message: String","description":"com.jluqgon214.hogarmate.model.RegisterResponse.message","location":"app/com.jluqgon214.hogarmate.model/-register-response/message.html","searchKeys":["message","val message: String","com.jluqgon214.hogarmate.model.RegisterResponse.message"]},{"name":"val onBackgroundDark: Color","description":"com.jluqgon214.hogarmate.ui.theme.onBackgroundDark","location":"app/com.jluqgon214.hogarmate.ui.theme/on-background-dark.html","searchKeys":["onBackgroundDark","val onBackgroundDark: Color","com.jluqgon214.hogarmate.ui.theme.onBackgroundDark"]},{"name":"val onBackgroundLight: Color","description":"com.jluqgon214.hogarmate.ui.theme.onBackgroundLight","location":"app/com.jluqgon214.hogarmate.ui.theme/on-background-light.html","searchKeys":["onBackgroundLight","val onBackgroundLight: Color","com.jluqgon214.hogarmate.ui.theme.onBackgroundLight"]},{"name":"val onErrorContainerDark: Color","description":"com.jluqgon214.hogarmate.ui.theme.onErrorContainerDark","location":"app/com.jluqgon214.hogarmate.ui.theme/on-error-container-dark.html","searchKeys":["onErrorContainerDark","val onErrorContainerDark: Color","com.jluqgon214.hogarmate.ui.theme.onErrorContainerDark"]},{"name":"val onErrorContainerLight: Color","description":"com.jluqgon214.hogarmate.ui.theme.onErrorContainerLight","location":"app/com.jluqgon214.hogarmate.ui.theme/on-error-container-light.html","searchKeys":["onErrorContainerLight","val onErrorContainerLight: Color","com.jluqgon214.hogarmate.ui.theme.onErrorContainerLight"]},{"name":"val onErrorDark: Color","description":"com.jluqgon214.hogarmate.ui.theme.onErrorDark","location":"app/com.jluqgon214.hogarmate.ui.theme/on-error-dark.html","searchKeys":["onErrorDark","val onErrorDark: Color","com.jluqgon214.hogarmate.ui.theme.onErrorDark"]},{"name":"val onErrorLight: Color","description":"com.jluqgon214.hogarmate.ui.theme.onErrorLight","location":"app/com.jluqgon214.hogarmate.ui.theme/on-error-light.html","searchKeys":["onErrorLight","val onErrorLight: Color","com.jluqgon214.hogarmate.ui.theme.onErrorLight"]},{"name":"val onPrimaryContainerDark: Color","description":"com.jluqgon214.hogarmate.ui.theme.onPrimaryContainerDark","location":"app/com.jluqgon214.hogarmate.ui.theme/on-primary-container-dark.html","searchKeys":["onPrimaryContainerDark","val onPrimaryContainerDark: Color","com.jluqgon214.hogarmate.ui.theme.onPrimaryContainerDark"]},{"name":"val onPrimaryContainerLight: Color","description":"com.jluqgon214.hogarmate.ui.theme.onPrimaryContainerLight","location":"app/com.jluqgon214.hogarmate.ui.theme/on-primary-container-light.html","searchKeys":["onPrimaryContainerLight","val onPrimaryContainerLight: Color","com.jluqgon214.hogarmate.ui.theme.onPrimaryContainerLight"]},{"name":"val onPrimaryDark: Color","description":"com.jluqgon214.hogarmate.ui.theme.onPrimaryDark","location":"app/com.jluqgon214.hogarmate.ui.theme/on-primary-dark.html","searchKeys":["onPrimaryDark","val onPrimaryDark: Color","com.jluqgon214.hogarmate.ui.theme.onPrimaryDark"]},{"name":"val onPrimaryLight: Color","description":"com.jluqgon214.hogarmate.ui.theme.onPrimaryLight","location":"app/com.jluqgon214.hogarmate.ui.theme/on-primary-light.html","searchKeys":["onPrimaryLight","val onPrimaryLight: Color","com.jluqgon214.hogarmate.ui.theme.onPrimaryLight"]},{"name":"val onSecondaryContainerDark: Color","description":"com.jluqgon214.hogarmate.ui.theme.onSecondaryContainerDark","location":"app/com.jluqgon214.hogarmate.ui.theme/on-secondary-container-dark.html","searchKeys":["onSecondaryContainerDark","val onSecondaryContainerDark: Color","com.jluqgon214.hogarmate.ui.theme.onSecondaryContainerDark"]},{"name":"val onSecondaryContainerLight: Color","description":"com.jluqgon214.hogarmate.ui.theme.onSecondaryContainerLight","location":"app/com.jluqgon214.hogarmate.ui.theme/on-secondary-container-light.html","searchKeys":["onSecondaryContainerLight","val onSecondaryContainerLight: Color","com.jluqgon214.hogarmate.ui.theme.onSecondaryContainerLight"]},{"name":"val onSecondaryDark: Color","description":"com.jluqgon214.hogarmate.ui.theme.onSecondaryDark","location":"app/com.jluqgon214.hogarmate.ui.theme/on-secondary-dark.html","searchKeys":["onSecondaryDark","val onSecondaryDark: Color","com.jluqgon214.hogarmate.ui.theme.onSecondaryDark"]},{"name":"val onSecondaryLight: Color","description":"com.jluqgon214.hogarmate.ui.theme.onSecondaryLight","location":"app/com.jluqgon214.hogarmate.ui.theme/on-secondary-light.html","searchKeys":["onSecondaryLight","val onSecondaryLight: Color","com.jluqgon214.hogarmate.ui.theme.onSecondaryLight"]},{"name":"val onSurfaceDark: Color","description":"com.jluqgon214.hogarmate.ui.theme.onSurfaceDark","location":"app/com.jluqgon214.hogarmate.ui.theme/on-surface-dark.html","searchKeys":["onSurfaceDark","val onSurfaceDark: Color","com.jluqgon214.hogarmate.ui.theme.onSurfaceDark"]},{"name":"val onSurfaceLight: Color","description":"com.jluqgon214.hogarmate.ui.theme.onSurfaceLight","location":"app/com.jluqgon214.hogarmate.ui.theme/on-surface-light.html","searchKeys":["onSurfaceLight","val onSurfaceLight: Color","com.jluqgon214.hogarmate.ui.theme.onSurfaceLight"]},{"name":"val onSurfaceVariantDark: Color","description":"com.jluqgon214.hogarmate.ui.theme.onSurfaceVariantDark","location":"app/com.jluqgon214.hogarmate.ui.theme/on-surface-variant-dark.html","searchKeys":["onSurfaceVariantDark","val onSurfaceVariantDark: Color","com.jluqgon214.hogarmate.ui.theme.onSurfaceVariantDark"]},{"name":"val onSurfaceVariantLight: Color","description":"com.jluqgon214.hogarmate.ui.theme.onSurfaceVariantLight","location":"app/com.jluqgon214.hogarmate.ui.theme/on-surface-variant-light.html","searchKeys":["onSurfaceVariantLight","val onSurfaceVariantLight: Color","com.jluqgon214.hogarmate.ui.theme.onSurfaceVariantLight"]},{"name":"val onTertiaryContainerDark: Color","description":"com.jluqgon214.hogarmate.ui.theme.onTertiaryContainerDark","location":"app/com.jluqgon214.hogarmate.ui.theme/on-tertiary-container-dark.html","searchKeys":["onTertiaryContainerDark","val onTertiaryContainerDark: Color","com.jluqgon214.hogarmate.ui.theme.onTertiaryContainerDark"]},{"name":"val onTertiaryContainerLight: Color","description":"com.jluqgon214.hogarmate.ui.theme.onTertiaryContainerLight","location":"app/com.jluqgon214.hogarmate.ui.theme/on-tertiary-container-light.html","searchKeys":["onTertiaryContainerLight","val onTertiaryContainerLight: Color","com.jluqgon214.hogarmate.ui.theme.onTertiaryContainerLight"]},{"name":"val onTertiaryDark: Color","description":"com.jluqgon214.hogarmate.ui.theme.onTertiaryDark","location":"app/com.jluqgon214.hogarmate.ui.theme/on-tertiary-dark.html","searchKeys":["onTertiaryDark","val onTertiaryDark: Color","com.jluqgon214.hogarmate.ui.theme.onTertiaryDark"]},{"name":"val onTertiaryLight: Color","description":"com.jluqgon214.hogarmate.ui.theme.onTertiaryLight","location":"app/com.jluqgon214.hogarmate.ui.theme/on-tertiary-light.html","searchKeys":["onTertiaryLight","val onTertiaryLight: Color","com.jluqgon214.hogarmate.ui.theme.onTertiaryLight"]},{"name":"val outlineDark: Color","description":"com.jluqgon214.hogarmate.ui.theme.outlineDark","location":"app/com.jluqgon214.hogarmate.ui.theme/outline-dark.html","searchKeys":["outlineDark","val outlineDark: Color","com.jluqgon214.hogarmate.ui.theme.outlineDark"]},{"name":"val outlineLight: Color","description":"com.jluqgon214.hogarmate.ui.theme.outlineLight","location":"app/com.jluqgon214.hogarmate.ui.theme/outline-light.html","searchKeys":["outlineLight","val outlineLight: Color","com.jluqgon214.hogarmate.ui.theme.outlineLight"]},{"name":"val outlineVariantDark: Color","description":"com.jluqgon214.hogarmate.ui.theme.outlineVariantDark","location":"app/com.jluqgon214.hogarmate.ui.theme/outline-variant-dark.html","searchKeys":["outlineVariantDark","val outlineVariantDark: Color","com.jluqgon214.hogarmate.ui.theme.outlineVariantDark"]},{"name":"val outlineVariantLight: Color","description":"com.jluqgon214.hogarmate.ui.theme.outlineVariantLight","location":"app/com.jluqgon214.hogarmate.ui.theme/outline-variant-light.html","searchKeys":["outlineVariantLight","val outlineVariantLight: Color","com.jluqgon214.hogarmate.ui.theme.outlineVariantLight"]},{"name":"val password: StateFlow<String>","description":"com.jluqgon214.hogarmate.viewModel.LoginViewModel.password","location":"app/com.jluqgon214.hogarmate.viewModel/-login-view-model/password.html","searchKeys":["password","val password: StateFlow<String>","com.jluqgon214.hogarmate.viewModel.LoginViewModel.password"]},{"name":"val password: StateFlow<String>","description":"com.jluqgon214.hogarmate.viewModel.RegisterViewModel.password","location":"app/com.jluqgon214.hogarmate.viewModel/-register-view-model/password.html","searchKeys":["password","val password: StateFlow<String>","com.jluqgon214.hogarmate.viewModel.RegisterViewModel.password"]},{"name":"val password: String","description":"com.jluqgon214.hogarmate.model.LoginRequest.password","location":"app/com.jluqgon214.hogarmate.model/-login-request/password.html","searchKeys":["password","val password: String","com.jluqgon214.hogarmate.model.LoginRequest.password"]},{"name":"val password: String","description":"com.jluqgon214.hogarmate.model.RegisterRequest.password","location":"app/com.jluqgon214.hogarmate.model/-register-request/password.html","searchKeys":["password","val password: String","com.jluqgon214.hogarmate.model.RegisterRequest.password"]},{"name":"val password: String","description":"com.jluqgon214.hogarmate.model.Usuario.password","location":"app/com.jluqgon214.hogarmate.model/-usuario/password.html","searchKeys":["password","val password: String","com.jluqgon214.hogarmate.model.Usuario.password"]},{"name":"val passwordRepeat: StateFlow<String>","description":"com.jluqgon214.hogarmate.viewModel.RegisterViewModel.passwordRepeat","location":"app/com.jluqgon214.hogarmate.viewModel/-register-view-model/password-repeat.html","searchKeys":["passwordRepeat","val passwordRepeat: StateFlow<String>","com.jluqgon214.hogarmate.viewModel.RegisterViewModel.passwordRepeat"]},{"name":"val passwordRepeat: String","description":"com.jluqgon214.hogarmate.model.RegisterRequest.passwordRepeat","location":"app/com.jluqgon214.hogarmate.model/-register-request/password-repeat.html","searchKeys":["passwordRepeat","val passwordRepeat: String","com.jluqgon214.hogarmate.model.RegisterRequest.passwordRepeat"]},{"name":"val primaryContainerDark: Color","description":"com.jluqgon214.hogarmate.ui.theme.primaryContainerDark","location":"app/com.jluqgon214.hogarmate.ui.theme/primary-container-dark.html","searchKeys":["primaryContainerDark","val primaryContainerDark: Color","com.jluqgon214.hogarmate.ui.theme.primaryContainerDark"]},{"name":"val primaryContainerLight: Color","description":"com.jluqgon214.hogarmate.ui.theme.primaryContainerLight","location":"app/com.jluqgon214.hogarmate.ui.theme/primary-container-light.html","searchKeys":["primaryContainerLight","val primaryContainerLight: Color","com.jluqgon214.hogarmate.ui.theme.primaryContainerLight"]},{"name":"val primaryDark: Color","description":"com.jluqgon214.hogarmate.ui.theme.primaryDark","location":"app/com.jluqgon214.hogarmate.ui.theme/primary-dark.html","searchKeys":["primaryDark","val primaryDark: Color","com.jluqgon214.hogarmate.ui.theme.primaryDark"]},{"name":"val primaryLight: Color","description":"com.jluqgon214.hogarmate.ui.theme.primaryLight","location":"app/com.jluqgon214.hogarmate.ui.theme/primary-light.html","searchKeys":["primaryLight","val primaryLight: Color","com.jluqgon214.hogarmate.ui.theme.primaryLight"]},{"name":"val provider: GoogleFont.Provider","description":"com.jluqgon214.hogarmate.ui.theme.provider","location":"app/com.jluqgon214.hogarmate.ui.theme/provider.html","searchKeys":["provider","val provider: GoogleFont.Provider","com.jluqgon214.hogarmate.ui.theme.provider"]},{"name":"val registerResponse: StateFlow<RegisterResponse?>","description":"com.jluqgon214.hogarmate.viewModel.RegisterViewModel.registerResponse","location":"app/com.jluqgon214.hogarmate.viewModel/-register-view-model/register-response.html","searchKeys":["registerResponse","val registerResponse: StateFlow<RegisterResponse?>","com.jluqgon214.hogarmate.viewModel.RegisterViewModel.registerResponse"]},{"name":"val rol: String?","description":"com.jluqgon214.hogarmate.model.RegisterRequest.rol","location":"app/com.jluqgon214.hogarmate.model/-register-request/rol.html","searchKeys":["rol","val rol: String?","com.jluqgon214.hogarmate.model.RegisterRequest.rol"]},{"name":"val roles: String","description":"com.jluqgon214.hogarmate.model.DTO.UsuarioConTareasDTO.roles","location":"app/com.jluqgon214.hogarmate.model.DTO/-usuario-con-tareas-d-t-o/roles.html","searchKeys":["roles","val roles: String","com.jluqgon214.hogarmate.model.DTO.UsuarioConTareasDTO.roles"]},{"name":"val roles: String","description":"com.jluqgon214.hogarmate.model.Usuario.roles","location":"app/com.jluqgon214.hogarmate.model/-usuario/roles.html","searchKeys":["roles","val roles: String","com.jluqgon214.hogarmate.model.Usuario.roles"]},{"name":"val scrimDark: Color","description":"com.jluqgon214.hogarmate.ui.theme.scrimDark","location":"app/com.jluqgon214.hogarmate.ui.theme/scrim-dark.html","searchKeys":["scrimDark","val scrimDark: Color","com.jluqgon214.hogarmate.ui.theme.scrimDark"]},{"name":"val scrimLight: Color","description":"com.jluqgon214.hogarmate.ui.theme.scrimLight","location":"app/com.jluqgon214.hogarmate.ui.theme/scrim-light.html","searchKeys":["scrimLight","val scrimLight: Color","com.jluqgon214.hogarmate.ui.theme.scrimLight"]},{"name":"val secondaryContainerDark: Color","description":"com.jluqgon214.hogarmate.ui.theme.secondaryContainerDark","location":"app/com.jluqgon214.hogarmate.ui.theme/secondary-container-dark.html","searchKeys":["secondaryContainerDark","val secondaryContainerDark: Color","com.jluqgon214.hogarmate.ui.theme.secondaryContainerDark"]},{"name":"val secondaryContainerLight: Color","description":"com.jluqgon214.hogarmate.ui.theme.secondaryContainerLight","location":"app/com.jluqgon214.hogarmate.ui.theme/secondary-container-light.html","searchKeys":["secondaryContainerLight","val secondaryContainerLight: Color","com.jluqgon214.hogarmate.ui.theme.secondaryContainerLight"]},{"name":"val secondaryDark: Color","description":"com.jluqgon214.hogarmate.ui.theme.secondaryDark","location":"app/com.jluqgon214.hogarmate.ui.theme/secondary-dark.html","searchKeys":["secondaryDark","val secondaryDark: Color","com.jluqgon214.hogarmate.ui.theme.secondaryDark"]},{"name":"val secondaryLight: Color","description":"com.jluqgon214.hogarmate.ui.theme.secondaryLight","location":"app/com.jluqgon214.hogarmate.ui.theme/secondary-light.html","searchKeys":["secondaryLight","val secondaryLight: Color","com.jluqgon214.hogarmate.ui.theme.secondaryLight"]},{"name":"val selectedBottomBarIndex: StateFlow<Int>","description":"com.jluqgon214.hogarmate.viewModel.AppViewModel.selectedBottomBarIndex","location":"app/com.jluqgon214.hogarmate.viewModel/-app-view-model/selected-bottom-bar-index.html","searchKeys":["selectedBottomBarIndex","val selectedBottomBarIndex: StateFlow<Int>","com.jluqgon214.hogarmate.viewModel.AppViewModel.selectedBottomBarIndex"]},{"name":"val showBottomBar: StateFlow<Boolean>","description":"com.jluqgon214.hogarmate.viewModel.AppViewModel.showBottomBar","location":"app/com.jluqgon214.hogarmate.viewModel/-app-view-model/show-bottom-bar.html","searchKeys":["showBottomBar","val showBottomBar: StateFlow<Boolean>","com.jluqgon214.hogarmate.viewModel.AppViewModel.showBottomBar"]},{"name":"val showDialog: StateFlow<Boolean>","description":"com.jluqgon214.hogarmate.viewModel.TasksViewModel.showDialog","location":"app/com.jluqgon214.hogarmate.viewModel/-tasks-view-model/show-dialog.html","searchKeys":["showDialog","val showDialog: StateFlow<Boolean>","com.jluqgon214.hogarmate.viewModel.TasksViewModel.showDialog"]},{"name":"val showEditDialog: StateFlow<Boolean>","description":"com.jluqgon214.hogarmate.viewModel.ProfileViewModel.showEditDialog","location":"app/com.jluqgon214.hogarmate.viewModel/-profile-view-model/show-edit-dialog.html","searchKeys":["showEditDialog","val showEditDialog: StateFlow<Boolean>","com.jluqgon214.hogarmate.viewModel.ProfileViewModel.showEditDialog"]},{"name":"val showFAB: StateFlow<Boolean>","description":"com.jluqgon214.hogarmate.viewModel.AppViewModel.showFAB","location":"app/com.jluqgon214.hogarmate.viewModel/-app-view-model/show-f-a-b.html","searchKeys":["showFAB","val showFAB: StateFlow<Boolean>","com.jluqgon214.hogarmate.viewModel.AppViewModel.showFAB"]},{"name":"val surfaceBrightDark: Color","description":"com.jluqgon214.hogarmate.ui.theme.surfaceBrightDark","location":"app/com.jluqgon214.hogarmate.ui.theme/surface-bright-dark.html","searchKeys":["surfaceBrightDark","val surfaceBrightDark: Color","com.jluqgon214.hogarmate.ui.theme.surfaceBrightDark"]},{"name":"val surfaceBrightLight: Color","description":"com.jluqgon214.hogarmate.ui.theme.surfaceBrightLight","location":"app/com.jluqgon214.hogarmate.ui.theme/surface-bright-light.html","searchKeys":["surfaceBrightLight","val surfaceBrightLight: Color","com.jluqgon214.hogarmate.ui.theme.surfaceBrightLight"]},{"name":"val surfaceContainerDark: Color","description":"com.jluqgon214.hogarmate.ui.theme.surfaceContainerDark","location":"app/com.jluqgon214.hogarmate.ui.theme/surface-container-dark.html","searchKeys":["surfaceContainerDark","val surfaceContainerDark: Color","com.jluqgon214.hogarmate.ui.theme.surfaceContainerDark"]},{"name":"val surfaceContainerHighDark: Color","description":"com.jluqgon214.hogarmate.ui.theme.surfaceContainerHighDark","location":"app/com.jluqgon214.hogarmate.ui.theme/surface-container-high-dark.html","searchKeys":["surfaceContainerHighDark","val surfaceContainerHighDark: Color","com.jluqgon214.hogarmate.ui.theme.surfaceContainerHighDark"]},{"name":"val surfaceContainerHighLight: Color","description":"com.jluqgon214.hogarmate.ui.theme.surfaceContainerHighLight","location":"app/com.jluqgon214.hogarmate.ui.theme/surface-container-high-light.html","searchKeys":["surfaceContainerHighLight","val surfaceContainerHighLight: Color","com.jluqgon214.hogarmate.ui.theme.surfaceContainerHighLight"]},{"name":"val surfaceContainerHighestDark: Color","description":"com.jluqgon214.hogarmate.ui.theme.surfaceContainerHighestDark","location":"app/com.jluqgon214.hogarmate.ui.theme/surface-container-highest-dark.html","searchKeys":["surfaceContainerHighestDark","val surfaceContainerHighestDark: Color","com.jluqgon214.hogarmate.ui.theme.surfaceContainerHighestDark"]},{"name":"val surfaceContainerHighestLight: Color","description":"com.jluqgon214.hogarmate.ui.theme.surfaceContainerHighestLight","location":"app/com.jluqgon214.hogarmate.ui.theme/surface-container-highest-light.html","searchKeys":["surfaceContainerHighestLight","val surfaceContainerHighestLight: Color","com.jluqgon214.hogarmate.ui.theme.surfaceContainerHighestLight"]},{"name":"val surfaceContainerLight: Color","description":"com.jluqgon214.hogarmate.ui.theme.surfaceContainerLight","location":"app/com.jluqgon214.hogarmate.ui.theme/surface-container-light.html","searchKeys":["surfaceContainerLight","val surfaceContainerLight: Color","com.jluqgon214.hogarmate.ui.theme.surfaceContainerLight"]},{"name":"val surfaceContainerLowDark: Color","description":"com.jluqgon214.hogarmate.ui.theme.surfaceContainerLowDark","location":"app/com.jluqgon214.hogarmate.ui.theme/surface-container-low-dark.html","searchKeys":["surfaceContainerLowDark","val surfaceContainerLowDark: Color","com.jluqgon214.hogarmate.ui.theme.surfaceContainerLowDark"]},{"name":"val surfaceContainerLowLight: Color","description":"com.jluqgon214.hogarmate.ui.theme.surfaceContainerLowLight","location":"app/com.jluqgon214.hogarmate.ui.theme/surface-container-low-light.html","searchKeys":["surfaceContainerLowLight","val surfaceContainerLowLight: Color","com.jluqgon214.hogarmate.ui.theme.surfaceContainerLowLight"]},{"name":"val surfaceContainerLowestDark: Color","description":"com.jluqgon214.hogarmate.ui.theme.surfaceContainerLowestDark","location":"app/com.jluqgon214.hogarmate.ui.theme/surface-container-lowest-dark.html","searchKeys":["surfaceContainerLowestDark","val surfaceContainerLowestDark: Color","com.jluqgon214.hogarmate.ui.theme.surfaceContainerLowestDark"]},{"name":"val surfaceContainerLowestLight: Color","description":"com.jluqgon214.hogarmate.ui.theme.surfaceContainerLowestLight","location":"app/com.jluqgon214.hogarmate.ui.theme/surface-container-lowest-light.html","searchKeys":["surfaceContainerLowestLight","val surfaceContainerLowestLight: Color","com.jluqgon214.hogarmate.ui.theme.surfaceContainerLowestLight"]},{"name":"val surfaceDark: Color","description":"com.jluqgon214.hogarmate.ui.theme.surfaceDark","location":"app/com.jluqgon214.hogarmate.ui.theme/surface-dark.html","searchKeys":["surfaceDark","val surfaceDark: Color","com.jluqgon214.hogarmate.ui.theme.surfaceDark"]},{"name":"val surfaceDimDark: Color","description":"com.jluqgon214.hogarmate.ui.theme.surfaceDimDark","location":"app/com.jluqgon214.hogarmate.ui.theme/surface-dim-dark.html","searchKeys":["surfaceDimDark","val surfaceDimDark: Color","com.jluqgon214.hogarmate.ui.theme.surfaceDimDark"]},{"name":"val surfaceDimLight: Color","description":"com.jluqgon214.hogarmate.ui.theme.surfaceDimLight","location":"app/com.jluqgon214.hogarmate.ui.theme/surface-dim-light.html","searchKeys":["surfaceDimLight","val surfaceDimLight: Color","com.jluqgon214.hogarmate.ui.theme.surfaceDimLight"]},{"name":"val surfaceLight: Color","description":"com.jluqgon214.hogarmate.ui.theme.surfaceLight","location":"app/com.jluqgon214.hogarmate.ui.theme/surface-light.html","searchKeys":["surfaceLight","val surfaceLight: Color","com.jluqgon214.hogarmate.ui.theme.surfaceLight"]},{"name":"val surfaceVariantDark: Color","description":"com.jluqgon214.hogarmate.ui.theme.surfaceVariantDark","location":"app/com.jluqgon214.hogarmate.ui.theme/surface-variant-dark.html","searchKeys":["surfaceVariantDark","val surfaceVariantDark: Color","com.jluqgon214.hogarmate.ui.theme.surfaceVariantDark"]},{"name":"val surfaceVariantLight: Color","description":"com.jluqgon214.hogarmate.ui.theme.surfaceVariantLight","location":"app/com.jluqgon214.hogarmate.ui.theme/surface-variant-light.html","searchKeys":["surfaceVariantLight","val surfaceVariantLight: Color","com.jluqgon214.hogarmate.ui.theme.surfaceVariantLight"]},{"name":"val tareas: List<TareaDTO>","description":"com.jluqgon214.hogarmate.model.DTO.UsuarioConTareasDTO.tareas","location":"app/com.jluqgon214.hogarmate.model.DTO/-usuario-con-tareas-d-t-o/tareas.html","searchKeys":["tareas","val tareas: List<TareaDTO>","com.jluqgon214.hogarmate.model.DTO.UsuarioConTareasDTO.tareas"]},{"name":"val tareas: StateFlow<List<Tarea>>","description":"com.jluqgon214.hogarmate.viewModel.TasksViewModel.tareas","location":"app/com.jluqgon214.hogarmate.viewModel/-tasks-view-model/tareas.html","searchKeys":["tareas","val tareas: StateFlow<List<Tarea>>","com.jluqgon214.hogarmate.viewModel.TasksViewModel.tareas"]},{"name":"val tareasCargando: StateFlow<Boolean>","description":"com.jluqgon214.hogarmate.viewModel.TasksViewModel.tareasCargando","location":"app/com.jluqgon214.hogarmate.viewModel/-tasks-view-model/tareas-cargando.html","searchKeys":["tareasCargando","val tareasCargando: StateFlow<Boolean>","com.jluqgon214.hogarmate.viewModel.TasksViewModel.tareasCargando"]},{"name":"val tareasCompletadas: MutableStateFlow<List<Tarea>>","description":"com.jluqgon214.hogarmate.viewModel.TasksViewModel.tareasCompletadas","location":"app/com.jluqgon214.hogarmate.viewModel/-tasks-view-model/tareas-completadas.html","searchKeys":["tareasCompletadas","val tareasCompletadas: MutableStateFlow<List<Tarea>>","com.jluqgon214.hogarmate.viewModel.TasksViewModel.tareasCompletadas"]},{"name":"val tareasPendientes: MutableStateFlow<List<Tarea>>","description":"com.jluqgon214.hogarmate.viewModel.TasksViewModel.tareasPendientes","location":"app/com.jluqgon214.hogarmate.viewModel/-tasks-view-model/tareas-pendientes.html","searchKeys":["tareasPendientes","val tareasPendientes: MutableStateFlow<List<Tarea>>","com.jluqgon214.hogarmate.viewModel.TasksViewModel.tareasPendientes"]},{"name":"val tertiaryContainerDark: Color","description":"com.jluqgon214.hogarmate.ui.theme.tertiaryContainerDark","location":"app/com.jluqgon214.hogarmate.ui.theme/tertiary-container-dark.html","searchKeys":["tertiaryContainerDark","val tertiaryContainerDark: Color","com.jluqgon214.hogarmate.ui.theme.tertiaryContainerDark"]},{"name":"val tertiaryContainerLight: Color","description":"com.jluqgon214.hogarmate.ui.theme.tertiaryContainerLight","location":"app/com.jluqgon214.hogarmate.ui.theme/tertiary-container-light.html","searchKeys":["tertiaryContainerLight","val tertiaryContainerLight: Color","com.jluqgon214.hogarmate.ui.theme.tertiaryContainerLight"]},{"name":"val tertiaryDark: Color","description":"com.jluqgon214.hogarmate.ui.theme.tertiaryDark","location":"app/com.jluqgon214.hogarmate.ui.theme/tertiary-dark.html","searchKeys":["tertiaryDark","val tertiaryDark: Color","com.jluqgon214.hogarmate.ui.theme.tertiaryDark"]},{"name":"val tertiaryLight: Color","description":"com.jluqgon214.hogarmate.ui.theme.tertiaryLight","location":"app/com.jluqgon214.hogarmate.ui.theme/tertiary-light.html","searchKeys":["tertiaryLight","val tertiaryLight: Color","com.jluqgon214.hogarmate.ui.theme.tertiaryLight"]},{"name":"val textoTop: StateFlow<String>","description":"com.jluqgon214.hogarmate.viewModel.AppViewModel.textoTop","location":"app/com.jluqgon214.hogarmate.viewModel/-app-view-model/texto-top.html","searchKeys":["textoTop","val textoTop: StateFlow<String>","com.jluqgon214.hogarmate.viewModel.AppViewModel.textoTop"]},{"name":"val token: String","description":"com.jluqgon214.hogarmate.model.LoginResponse.token","location":"app/com.jluqgon214.hogarmate.model/-login-response/token.html","searchKeys":["token","val token: String","com.jluqgon214.hogarmate.model.LoginResponse.token"]},{"name":"val username: StateFlow<String>","description":"com.jluqgon214.hogarmate.viewModel.ProfileViewModel.username","location":"app/com.jluqgon214.hogarmate.viewModel/-profile-view-model/username.html","searchKeys":["username","val username: StateFlow<String>","com.jluqgon214.hogarmate.viewModel.ProfileViewModel.username"]},{"name":"val username: StateFlow<String>","description":"com.jluqgon214.hogarmate.viewModel.RegisterViewModel.username","location":"app/com.jluqgon214.hogarmate.viewModel/-register-view-model/username.html","searchKeys":["username","val username: StateFlow<String>","com.jluqgon214.hogarmate.viewModel.RegisterViewModel.username"]},{"name":"val username: String","description":"com.jluqgon214.hogarmate.model.DTO.UsuarioConTareasDTO.username","location":"app/com.jluqgon214.hogarmate.model.DTO/-usuario-con-tareas-d-t-o/username.html","searchKeys":["username","val username: String","com.jluqgon214.hogarmate.model.DTO.UsuarioConTareasDTO.username"]},{"name":"val username: String","description":"com.jluqgon214.hogarmate.model.RegisterRequest.username","location":"app/com.jluqgon214.hogarmate.model/-register-request/username.html","searchKeys":["username","val username: String","com.jluqgon214.hogarmate.model.RegisterRequest.username"]},{"name":"val username: String","description":"com.jluqgon214.hogarmate.model.Usuario.username","location":"app/com.jluqgon214.hogarmate.model/-usuario/username.html","searchKeys":["username","val username: String","com.jluqgon214.hogarmate.model.Usuario.username"]},{"name":"val usuario: MutableStateFlow<UsuarioConTareasDTO?>","description":"com.jluqgon214.hogarmate.viewModel.TasksViewModel.usuario","location":"app/com.jluqgon214.hogarmate.viewModel/-tasks-view-model/usuario.html","searchKeys":["usuario","val usuario: MutableStateFlow<UsuarioConTareasDTO?>","com.jluqgon214.hogarmate.viewModel.TasksViewModel.usuario"]},{"name":"val usuario: StateFlow<Usuario?>","description":"com.jluqgon214.hogarmate.viewModel.ProfileViewModel.usuario","location":"app/com.jluqgon214.hogarmate.viewModel/-profile-view-model/usuario.html","searchKeys":["usuario","val usuario: StateFlow<Usuario?>","com.jluqgon214.hogarmate.viewModel.ProfileViewModel.usuario"]},{"name":"val usuario: Usuario","description":"com.jluqgon214.hogarmate.model.Tarea.usuario","location":"app/com.jluqgon214.hogarmate.model/-tarea/usuario.html","searchKeys":["usuario","val usuario: Usuario","com.jluqgon214.hogarmate.model.Tarea.usuario"]},{"name":"val usuariosCargando: MutableStateFlow<Boolean>","description":"com.jluqgon214.hogarmate.viewModel.AdminViewModel.usuariosCargando","location":"app/com.jluqgon214.hogarmate.viewModel/-admin-view-model/usuarios-cargando.html","searchKeys":["usuariosCargando","val usuariosCargando: MutableStateFlow<Boolean>","com.jluqgon214.hogarmate.viewModel.AdminViewModel.usuariosCargando"]},{"name":"val usuariosConTareas: MutableStateFlow<List<UsuarioConTareasDTO>>","description":"com.jluqgon214.hogarmate.viewModel.AdminViewModel.usuariosConTareas","location":"app/com.jluqgon214.hogarmate.viewModel/-admin-view-model/usuarios-con-tareas.html","searchKeys":["usuariosConTareas","val usuariosConTareas: MutableStateFlow<List<UsuarioConTareasDTO>>","com.jluqgon214.hogarmate.viewModel.AdminViewModel.usuariosConTareas"]}]
